{
	"$schema": "http://schema.management.azure.com/schemas/2015-01-01/deploymentTemplate.json#",
	"contentVersion": "1.0.0.0",
	"parameters": {
		"factoryName": {
			"type": "string",
			"metadata": "Data Factory name",
			"defaultValue": "VSADF2606"
		},
		"AzureDataLakeStorage1_accountKey": {
			"type": "secureString",
			"metadata": "Secure string for 'accountKey' of 'AzureDataLakeStorage1'"
		},
		"AzureDataLakeStorage1_properties_typeProperties_url": {
			"type": "string",
			"defaultValue": "https://storagevijaydemo.dfs.core.windows.net/"
		},
		"SqlServer1_properties_typeProperties_server": {
			"type": "string",
			"defaultValue": "@{linkedService().serverName}"
		},
		"SqlServer1_properties_typeProperties_database": {
			"type": "string",
			"defaultValue": "@{linkedService().dbName}"
		},
		"SqlServer1_properties_typeProperties_userName": {
			"type": "string",
			"defaultValue": "@{linkedService().userName}"
		},
		"Event Based Trigger_properties_typeProperties_scope": {
			"type": "string",
			"defaultValue": "/subscriptions/5e8b1b54-b36b-40df-8776-56bfad5e0633/resourceGroups/vijay_rg/providers/Microsoft.Storage/storageAccounts/storagevijaydemo"
		},
		"EventBasedTrigger_SetVariable_properties_Set_Variable_Pipeline_parameters_FileName": {
			"type": "string",
			"defaultValue": "@triggerBody.fileName"
		},
		"EventBasedTrigger_SetVariable_properties_typeProperties_scope": {
			"type": "string",
			"defaultValue": "/subscriptions/5e8b1b54-b36b-40df-8776-56bfad5e0633/resourceGroups/vijay_rg/providers/Microsoft.Storage/storageAccounts/storagevijaydemo"
		}
	},
	"variables": {
		"factoryId": "[concat('Microsoft.DataFactory/factories/', parameters('factoryName'))]"
	},
	"resources": [
		{
			"name": "[concat(parameters('factoryName'), '/Event Base Triggers Demo')]",
			"type": "Microsoft.DataFactory/factories/pipelines",
			"apiVersion": "2018-06-01",
			"properties": {
				"activities": [
					{
						"name": "Copy data1",
						"type": "Copy",
						"dependsOn": [],
						"policy": {
							"timeout": "0.12:00:00",
							"retry": 0,
							"retryIntervalInSeconds": 30,
							"secureOutput": false,
							"secureInput": false
						},
						"userProperties": [],
						"typeProperties": {
							"source": {
								"type": "DelimitedTextSource",
								"storeSettings": {
									"type": "AzureBlobFSReadSettings",
									"recursive": true,
									"enablePartitionDiscovery": false
								},
								"formatSettings": {
									"type": "DelimitedTextReadSettings"
								}
							},
							"sink": {
								"type": "DelimitedTextSink",
								"storeSettings": {
									"type": "AzureBlobFSWriteSettings",
									"copyBehavior": "PreserveHierarchy"
								},
								"formatSettings": {
									"type": "DelimitedTextWriteSettings",
									"quoteAllText": true,
									"fileExtension": ".txt"
								}
							},
							"enableStaging": false,
							"translator": {
								"type": "TabularTranslator",
								"typeConversion": true,
								"typeConversionSettings": {
									"allowDataTruncation": true,
									"treatBooleanAsNumber": false
								}
							}
						},
						"inputs": [
							{
								"referenceName": "Input_CSV_DataSet_data_csv",
								"type": "DatasetReference",
								"parameters": {}
							}
						],
						"outputs": [
							{
								"referenceName": "Output_CSV_DataSet_data_csv",
								"type": "DatasetReference",
								"parameters": {}
							}
						]
					}
				],
				"policy": {
					"elapsedTimeMetric": {}
				},
				"parameters": {
					"SourcePath": {
						"type": "string"
					},
					"SourceFile": {
						"type": "string"
					}
				},
				"annotations": [],
				"lastPublishTime": "2026-06-26T11:11:25Z"
			},
			"dependsOn": [
				"[concat(variables('factoryId'), '/datasets/Input_CSV_DataSet_data_csv')]",
				"[concat(variables('factoryId'), '/datasets/Output_CSV_DataSet_data_csv')]"
			]
		},
		{
			"name": "[concat(parameters('factoryName'), '/Parameterized_Pipeline_Demo')]",
			"type": "Microsoft.DataFactory/factories/pipelines",
			"apiVersion": "2018-06-01",
			"properties": {
				"activities": [
					{
						"name": "Copy data1",
						"type": "Copy",
						"dependsOn": [],
						"policy": {
							"timeout": "0.12:00:00",
							"retry": 0,
							"retryIntervalInSeconds": 30,
							"secureOutput": false,
							"secureInput": false
						},
						"userProperties": [],
						"typeProperties": {
							"source": {
								"type": "SqlServerSource",
								"queryTimeout": "02:00:00",
								"partitionOption": "None"
							},
							"sink": {
								"type": "SqlServerSink",
								"writeBehavior": "insert",
								"sqlWriterUseTableLock": false
							},
							"enableStaging": false,
							"translator": {
								"type": "TabularTranslator",
								"typeConversion": true,
								"typeConversionSettings": {
									"allowDataTruncation": true,
									"treatBooleanAsNumber": false
								}
							}
						},
						"inputs": [
							{
								"referenceName": "ParamSqlServerTable",
								"type": "DatasetReference",
								"parameters": {
									"datasetServer": {
										"value": "@pipeline().parameters.serverNameFromPipeline",
										"type": "Expression"
									},
									"datasetDb": {
										"value": "@pipeline().parameters.dbNameFromPipeline",
										"type": "Expression"
									},
									"datasetUserName": {
										"value": "@pipeline().parameters.userNameFromPipeline",
										"type": "Expression"
									},
									"datasetPassword": {
										"value": "@pipeline().parameters.passwordNameFromPipeline",
										"type": "Expression"
									},
									"datasetDbo": {
										"value": "@pipeline().parameters.dboNameFromPipeline",
										"type": "Expression"
									},
									"datasetTable": {
										"value": "@pipeline().parameters.sourceTableNameFromPipeline",
										"type": "Expression"
									}
								}
							}
						],
						"outputs": [
							{
								"referenceName": "ParamSqlServerTable",
								"type": "DatasetReference",
								"parameters": {
									"datasetServer": {
										"value": "@pipeline().parameters.serverNameFromPipeline",
										"type": "Expression"
									},
									"datasetDb": {
										"value": "@pipeline().parameters.dbNameFromPipeline",
										"type": "Expression"
									},
									"datasetUserName": {
										"value": "@pipeline().parameters.userNameFromPipeline",
										"type": "Expression"
									},
									"datasetPassword": {
										"value": "@pipeline().parameters.passwordNameFromPipeline",
										"type": "Expression"
									},
									"datasetDbo": {
										"value": "@pipeline().parameters.dboNameFromPipeline",
										"type": "Expression"
									},
									"datasetTable": {
										"value": "@pipeline().parameters.destinationTableNameFromPipeline",
										"type": "Expression"
									}
								}
							}
						]
					}
				],
				"policy": {
					"elapsedTimeMetric": {}
				},
				"parameters": {
					"serverNameFromPipeline": {
						"type": "string"
					},
					"dbNameFromPipeline": {
						"type": "string"
					},
					"passwordNameFromPipeline": {
						"type": "string"
					},
					"userNameFromPipeline": {
						"type": "string"
					},
					"dboNameFromPipeline": {
						"type": "string"
					},
					"sourceTableNameFromPipeline": {
						"type": "string"
					},
					"destinationTableNameFromPipeline": {
						"type": "string"
					}
				},
				"annotations": []
			},
			"dependsOn": [
				"[concat(variables('factoryId'), '/datasets/ParamSqlServerTable')]"
			]
		},
		{
			"name": "[concat(parameters('factoryName'), '/Storage_Account_File_Movement')]",
			"type": "Microsoft.DataFactory/factories/pipelines",
			"apiVersion": "2018-06-01",
			"properties": {
				"activities": [
					{
						"name": "Copy data1",
						"type": "Copy",
						"dependsOn": [],
						"policy": {
							"timeout": "0.12:00:00",
							"retry": 0,
							"retryIntervalInSeconds": 30,
							"secureOutput": false,
							"secureInput": false
						},
						"userProperties": [],
						"typeProperties": {
							"source": {
								"type": "DelimitedTextSource",
								"storeSettings": {
									"type": "AzureBlobFSReadSettings",
									"recursive": true,
									"enablePartitionDiscovery": false
								},
								"formatSettings": {
									"type": "DelimitedTextReadSettings"
								}
							},
							"sink": {
								"type": "DelimitedTextSink",
								"storeSettings": {
									"type": "AzureBlobFSWriteSettings",
									"copyBehavior": "PreserveHierarchy"
								},
								"formatSettings": {
									"type": "DelimitedTextWriteSettings",
									"quoteAllText": true,
									"fileExtension": ".txt"
								}
							},
							"enableStaging": false,
							"translator": {
								"type": "TabularTranslator",
								"typeConversion": true,
								"typeConversionSettings": {
									"allowDataTruncation": true,
									"treatBooleanAsNumber": false
								}
							}
						},
						"inputs": [
							{
								"referenceName": "Input_CSV_DataSet_data_csv",
								"type": "DatasetReference",
								"parameters": {}
							}
						],
						"outputs": [
							{
								"referenceName": "Output_CSV_DataSet_data_csv",
								"type": "DatasetReference",
								"parameters": {}
							}
						]
					}
				],
				"policy": {
					"elapsedTimeMetric": {}
				},
				"annotations": [],
				"lastPublishTime": "2026-06-26T11:11:25Z"
			},
			"dependsOn": [
				"[concat(variables('factoryId'), '/datasets/Input_CSV_DataSet_data_csv')]",
				"[concat(variables('factoryId'), '/datasets/Output_CSV_DataSet_data_csv')]"
			]
		},
		{
			"name": "[concat(parameters('factoryName'), '/Input_CSV_DataSet_data_csv')]",
			"type": "Microsoft.DataFactory/factories/datasets",
			"apiVersion": "2018-06-01",
			"properties": {
				"linkedServiceName": {
					"referenceName": "AzureDataLakeStorage1",
					"type": "LinkedServiceReference"
				},
				"annotations": [],
				"type": "DelimitedText",
				"typeProperties": {
					"location": {
						"type": "AzureBlobFSLocation",
						"fileName": "data.csv",
						"folderPath": "input",
						"fileSystem": "adfdemo"
					},
					"columnDelimiter": ",",
					"escapeChar": "\\",
					"firstRowAsHeader": true,
					"quoteChar": "\""
				},
				"schema": [
					{
						"name": "emp_id",
						"type": "String"
					},
					{
						"name": "emp_name",
						"type": "String"
					},
					{
						"name": "salary",
						"type": "String"
					}
				]
			},
			"dependsOn": [
				"[concat(variables('factoryId'), '/linkedServices/AzureDataLakeStorage1')]"
			]
		},
		{
			"name": "[concat(parameters('factoryName'), '/Output_CSV_DataSet_data_csv')]",
			"type": "Microsoft.DataFactory/factories/datasets",
			"apiVersion": "2018-06-01",
			"properties": {
				"linkedServiceName": {
					"referenceName": "AzureDataLakeStorage1",
					"type": "LinkedServiceReference"
				},
				"annotations": [],
				"type": "DelimitedText",
				"typeProperties": {
					"location": {
						"type": "AzureBlobFSLocation",
						"fileName": "data.csv",
						"folderPath": "output",
						"fileSystem": "adfdemo"
					},
					"columnDelimiter": ",",
					"escapeChar": "\\",
					"firstRowAsHeader": true,
					"quoteChar": "\""
				},
				"schema": []
			},
			"dependsOn": [
				"[concat(variables('factoryId'), '/linkedServices/AzureDataLakeStorage1')]"
			]
		},
		{
			"name": "[concat(parameters('factoryName'), '/ParamSqlServerTable')]",
			"type": "Microsoft.DataFactory/factories/datasets",
			"apiVersion": "2018-06-01",
			"properties": {
				"linkedServiceName": {
					"referenceName": "SqlServer1",
					"type": "LinkedServiceReference",
					"parameters": {
						"serverName": {
							"value": "@dataset().datasetServer",
							"type": "Expression"
						},
						"dbName": {
							"value": "@dataset().datasetDb",
							"type": "Expression"
						},
						"userName": {
							"value": "@dataset().datasetUserName",
							"type": "Expression"
						},
						"password": {
							"value": "@dataset().datasetPassword",
							"type": "Expression"
						}
					}
				},
				"parameters": {
					"datasetServer": {
						"type": "string"
					},
					"datasetDb": {
						"type": "string"
					},
					"datasetUserName": {
						"type": "string"
					},
					"datasetPassword": {
						"type": "string"
					},
					"datasetDbo": {
						"type": "string"
					},
					"datasetTable": {
						"type": "string"
					}
				},
				"annotations": [],
				"type": "SqlServerTable",
				"schema": [],
				"typeProperties": {
					"schema": {
						"value": "@dataset().datasetDbo",
						"type": "Expression"
					},
					"table": {
						"value": "@dataset().datasetTable",
						"type": "Expression"
					}
				}
			},
			"dependsOn": [
				"[concat(variables('factoryId'), '/linkedServices/SqlServer1')]"
			]
		},
		{
			"name": "[concat(parameters('factoryName'), '/AzureDataLakeStorage1')]",
			"type": "Microsoft.DataFactory/factories/linkedServices",
			"apiVersion": "2018-06-01",
			"properties": {
				"annotations": [],
				"type": "AzureBlobFS",
				"typeProperties": {
					"url": "[parameters('AzureDataLakeStorage1_properties_typeProperties_url')]",
					"accountKey": {
						"type": "SecureString",
						"value": "[parameters('AzureDataLakeStorage1_accountKey')]"
					}
				}
			},
			"dependsOn": []
		},
		{
			"name": "[concat(parameters('factoryName'), '/SqlServer1')]",
			"type": "Microsoft.DataFactory/factories/linkedServices",
			"apiVersion": "2018-06-01",
			"properties": {
				"parameters": {
					"serverName": {
						"type": "string"
					},
					"dbName": {
						"type": "string"
					},
					"userName": {
						"type": "string"
					},
					"password": {
						"type": "string"
					}
				},
				"annotations": [],
				"type": "SqlServer",
				"typeProperties": {
					"server": "[parameters('SqlServer1_properties_typeProperties_server')]",
					"database": "[parameters('SqlServer1_properties_typeProperties_database')]",
					"encrypt": "mandatory",
					"trustServerCertificate": false,
					"authenticationType": "SQL",
					"userName": "[parameters('SqlServer1_properties_typeProperties_userName')]",
					"password": "@{linkedService().password}"
				}
			},
			"dependsOn": []
		},
		{
			"name": "[concat(parameters('factoryName'), '/Event Based Trigger')]",
			"type": "Microsoft.DataFactory/factories/triggers",
			"apiVersion": "2018-06-01",
			"properties": {
				"annotations": [],
				"runtimeState": "Stopped",
				"pipelines": [
					{
						"pipelineReference": {
							"referenceName": "Event Base Triggers Demo",
							"type": "PipelineReference"
						},
						"parameters": {}
					}
				],
				"type": "BlobEventsTrigger",
				"typeProperties": {
					"blobPathBeginsWith": "/adfdemo/blobs/input/",
					"blobPathEndsWith": ".csv",
					"ignoreEmptyBlobs": true,
					"scope": "[parameters('Event Based Trigger_properties_typeProperties_scope')]",
					"events": [
						"Microsoft.Storage.BlobCreated"
					]
				}
			},
			"dependsOn": [
				"[concat(variables('factoryId'), '/pipelines/Event Base Triggers Demo')]"
			]
		},
		{
			"name": "[concat(parameters('factoryName'), '/ParameterizedTrigger')]",
			"type": "Microsoft.DataFactory/factories/triggers",
			"apiVersion": "2018-06-01",
			"properties": {
				"annotations": [],
				"runtimeState": "Stopped",
				"pipelines": [
					{
						"pipelineReference": {
							"referenceName": "Parameterized_Pipeline_Demo",
							"type": "PipelineReference"
						},
						"parameters": {}
					}
				],
				"type": "ScheduleTrigger",
				"typeProperties": {
					"recurrence": {
						"frequency": "Minute",
						"interval": 15,
						"startTime": "2026-06-26T16:14:00",
						"timeZone": "India Standard Time"
					}
				}
			},
			"dependsOn": [
				"[concat(variables('factoryId'), '/pipelines/Parameterized_Pipeline_Demo')]"
			]
		},
		{
			"name": "[concat(parameters('factoryName'), '/Trigger1')]",
			"type": "Microsoft.DataFactory/factories/triggers",
			"apiVersion": "2018-06-01",
			"properties": {
				"annotations": [],
				"runtimeState": "Stopped",
				"pipelines": [
					{
						"pipelineReference": {
							"referenceName": "Storage_Account_File_Movement",
							"type": "PipelineReference"
						},
						"parameters": {}
					}
				],
				"type": "ScheduleTrigger",
				"typeProperties": {
					"recurrence": {
						"frequency": "Hour",
						"interval": 1,
						"startTime": "2026-06-26T12:00:00",
						"timeZone": "India Standard Time"
					}
				}
			},
			"dependsOn": [
				"[concat(variables('factoryId'), '/pipelines/Storage_Account_File_Movement')]"
			]
		},
		{
			"name": "[concat(parameters('factoryName'), '/Mapping_Copy_Activity_With_Settings')]",
			"type": "Microsoft.DataFactory/factories/pipelines",
			"apiVersion": "2018-06-01",
			"properties": {
				"activities": [
					{
						"name": "Copy data1",
						"type": "Copy",
						"dependsOn": [],
						"policy": {
							"timeout": "0.12:00:00",
							"retry": 0,
							"retryIntervalInSeconds": 30,
							"secureOutput": false,
							"secureInput": false
						},
						"userProperties": [
							{
								"name": "Source",
								"value": "adfdemo/input/data.csv"
							},
							{
								"name": "Target",
								"value": "adfdemo/output/data.csv"
							}
						],
						"typeProperties": {
							"source": {
								"type": "DelimitedTextSource",
								"storeSettings": {
									"type": "AzureBlobFSReadSettings",
									"recursive": true,
									"enablePartitionDiscovery": false
								},
								"formatSettings": {
									"type": "DelimitedTextReadSettings"
								}
							},
							"sink": {
								"type": "DelimitedTextSink",
								"storeSettings": {
									"type": "AzureBlobFSWriteSettings",
									"copyBehavior": "PreserveHierarchy"
								},
								"formatSettings": {
									"type": "DelimitedTextWriteSettings",
									"quoteAllText": true,
									"fileExtension": ".txt"
								}
							},
							"enableStaging": false,
							"logSettings": {
								"enableCopyActivityLog": true,
								"copyActivityLogSettings": {
									"logLevel": "Info",
									"enableReliableLogging": false
								},
								"logLocationSettings": {
									"linkedServiceName": {
										"referenceName": "AzureDataLakeStorage1",
										"type": "LinkedServiceReference"
									},
									"path": "adfdemo/errorlog/"
								}
							},
							"translator": {
								"type": "TabularTranslator",
								"mappings": [
									{
										"source": {
											"name": "emp_name",
											"type": "String",
											"physicalType": "String"
										},
										"sink": {
											"name": "emp_name",
											"type": "String",
											"physicalType": "String"
										}
									},
									{
										"source": {
											"name": "salary",
											"type": "String",
											"physicalType": "String"
										},
										"sink": {
											"name": "salary",
											"type": "String",
											"physicalType": "String"
										}
									},
									{
										"source": {
											"name": "emp_id",
											"type": "String",
											"physicalType": "String"
										},
										"sink": {
											"name": "emp_id",
											"type": "String",
											"physicalType": "String"
										}
									}
								],
								"typeConversion": true,
								"typeConversionSettings": {
									"allowDataTruncation": true,
									"treatBooleanAsNumber": false
								}
							}
						},
						"inputs": [
							{
								"referenceName": "Input_CSV_DataSet_data_csv",
								"type": "DatasetReference",
								"parameters": {}
							}
						],
						"outputs": [
							{
								"referenceName": "Output_CSV_DataSet_data_csv",
								"type": "DatasetReference",
								"parameters": {}
							}
						]
					}
				],
				"policy": {
					"elapsedTimeMetric": {}
				},
				"annotations": []
			},
			"dependsOn": [
				"[concat(variables('factoryId'), '/datasets/Input_CSV_DataSet_data_csv')]",
				"[concat(variables('factoryId'), '/datasets/Output_CSV_DataSet_data_csv')]",
				"[concat(variables('factoryId'), '/linkedServices/AzureDataLakeStorage1')]"
			]
		},
		{
			"name": "[concat(parameters('factoryName'), '/Delete_Activity')]",
			"type": "Microsoft.DataFactory/factories/pipelines",
			"apiVersion": "2018-06-01",
			"properties": {
				"activities": [
					{
						"name": "Delete1",
						"type": "Delete",
						"dependsOn": [],
						"policy": {
							"timeout": "0.12:00:00",
							"retry": 0,
							"retryIntervalInSeconds": 30,
							"secureOutput": false,
							"secureInput": false
						},
						"userProperties": [],
						"typeProperties": {
							"dataset": {
								"referenceName": "Output_CSV_DataSet_data_csv",
								"type": "DatasetReference",
								"parameters": {}
							},
							"logStorageSettings": {
								"linkedServiceName": {
									"referenceName": "AzureDataLakeStorage1",
									"type": "LinkedServiceReference"
								},
								"path": "adfdemo/errorlog"
							},
							"enableLogging": true,
							"storeSettings": {
								"type": "AzureBlobFSReadSettings",
								"recursive": true,
								"wildcardFileName": "*.csv",
								"enablePartitionDiscovery": false
							}
						}
					}
				],
				"policy": {
					"elapsedTimeMetric": {}
				},
				"annotations": []
			},
			"dependsOn": [
				"[concat(variables('factoryId'), '/datasets/Output_CSV_DataSet_data_csv')]",
				"[concat(variables('factoryId'), '/linkedServices/AzureDataLakeStorage1')]"
			]
		},
		{
			"name": "[concat(parameters('factoryName'), '/Set_Variable_Pipeline')]",
			"type": "Microsoft.DataFactory/factories/pipelines",
			"apiVersion": "2018-06-01",
			"properties": {
				"activities": [
					{
						"name": "Set variable1",
						"type": "SetVariable",
						"dependsOn": [],
						"policy": {
							"secureOutput": false,
							"secureInput": false
						},
						"userProperties": [],
						"typeProperties": {
							"variableName": "FileType",
							"value": {
								"value": "@replace(pipeline().parameters.FileName,'Sales','')",
								"type": "Expression"
							}
						}
					},
					{
						"name": "If Condition1",
						"type": "IfCondition",
						"dependsOn": [
							{
								"activity": "Set variable1",
								"dependencyConditions": [
									"Succeeded"
								]
							}
						],
						"userProperties": [],
						"typeProperties": {
							"expression": {
								"value": "@equals(variables('FileType'),'Hourly')",
								"type": "Expression"
							},
							"ifFalseActivities": [
								{
									"name": "Copy data2",
									"type": "Copy",
									"dependsOn": [],
									"policy": {
										"timeout": "0.12:00:00",
										"retry": 0,
										"retryIntervalInSeconds": 30,
										"secureOutput": false,
										"secureInput": false
									},
									"userProperties": [],
									"typeProperties": {
										"source": {
											"type": "DelimitedTextSource",
											"storeSettings": {
												"type": "AzureBlobFSReadSettings",
												"recursive": true,
												"enablePartitionDiscovery": false
											},
											"formatSettings": {
												"type": "DelimitedTextReadSettings"
											}
										},
										"sink": {
											"type": "DelimitedTextSink",
											"storeSettings": {
												"type": "AzureBlobFSWriteSettings"
											},
											"formatSettings": {
												"type": "DelimitedTextWriteSettings",
												"quoteAllText": true,
												"fileExtension": ".txt"
											}
										},
										"enableStaging": false,
										"translator": {
											"type": "TabularTranslator",
											"typeConversion": true,
											"typeConversionSettings": {
												"allowDataTruncation": true,
												"treatBooleanAsNumber": false
											}
										}
									},
									"inputs": [
										{
											"referenceName": "DailyHourlySourceDataset",
											"type": "DatasetReference",
											"parameters": {}
										}
									],
									"outputs": [
										{
											"referenceName": "DailyFileDataset",
											"type": "DatasetReference",
											"parameters": {}
										}
									]
								}
							],
							"ifTrueActivities": [
								{
									"name": "Copy data1",
									"type": "Copy",
									"dependsOn": [],
									"policy": {
										"timeout": "0.12:00:00",
										"retry": 0,
										"retryIntervalInSeconds": 30,
										"secureOutput": false,
										"secureInput": false
									},
									"userProperties": [],
									"typeProperties": {
										"source": {
											"type": "DelimitedTextSource",
											"storeSettings": {
												"type": "AzureBlobFSReadSettings",
												"recursive": true,
												"enablePartitionDiscovery": false
											},
											"formatSettings": {
												"type": "DelimitedTextReadSettings"
											}
										},
										"sink": {
											"type": "DelimitedTextSink",
											"storeSettings": {
												"type": "AzureBlobFSWriteSettings"
											},
											"formatSettings": {
												"type": "DelimitedTextWriteSettings",
												"quoteAllText": true,
												"fileExtension": ".txt"
											}
										},
										"enableStaging": false,
										"translator": {
											"type": "TabularTranslator",
											"typeConversion": true,
											"typeConversionSettings": {
												"allowDataTruncation": true,
												"treatBooleanAsNumber": false
											}
										}
									},
									"inputs": [
										{
											"referenceName": "DailyHourlySourceDataset",
											"type": "DatasetReference",
											"parameters": {}
										}
									],
									"outputs": [
										{
											"referenceName": "HourlyFileDataset",
											"type": "DatasetReference",
											"parameters": {}
										}
									]
								}
							]
						}
					}
				],
				"policy": {
					"elapsedTimeMetric": {}
				},
				"parameters": {
					"FileName": {
						"type": "string"
					}
				},
				"variables": {
					"FileType": {
						"type": "String"
					}
				},
				"annotations": []
			},
			"dependsOn": [
				"[concat(variables('factoryId'), '/datasets/DailyHourlySourceDataset')]",
				"[concat(variables('factoryId'), '/datasets/HourlyFileDataset')]",
				"[concat(variables('factoryId'), '/datasets/DailyFileDataset')]"
			]
		},
		{
			"name": "[concat(parameters('factoryName'), '/EventBasedTrigger_SetVariable')]",
			"type": "Microsoft.DataFactory/factories/triggers",
			"apiVersion": "2018-06-01",
			"properties": {
				"annotations": [],
				"runtimeState": "Stopped",
				"pipelines": [
					{
						"pipelineReference": {
							"referenceName": "Set_Variable_Pipeline",
							"type": "PipelineReference"
						},
						"parameters": {
							"FileName": "[parameters('EventBasedTrigger_SetVariable_properties_Set_Variable_Pipeline_parameters_FileName')]"
						}
					}
				],
				"type": "BlobEventsTrigger",
				"typeProperties": {
					"blobPathBeginsWith": "/adfdemo/blobs/input/",
					"blobPathEndsWith": "*.csv",
					"ignoreEmptyBlobs": true,
					"scope": "[parameters('EventBasedTrigger_SetVariable_properties_typeProperties_scope')]",
					"events": [
						"Microsoft.Storage.BlobCreated"
					]
				}
			},
			"dependsOn": [
				"[concat(variables('factoryId'), '/pipelines/Set_Variable_Pipeline')]"
			]
		},
		{
			"name": "[concat(parameters('factoryName'), '/HourlyFileDataset')]",
			"type": "Microsoft.DataFactory/factories/datasets",
			"apiVersion": "2018-06-01",
			"properties": {
				"linkedServiceName": {
					"referenceName": "AzureDataLakeStorage1",
					"type": "LinkedServiceReference"
				},
				"annotations": [],
				"type": "DelimitedText",
				"typeProperties": {
					"location": {
						"type": "AzureBlobFSLocation",
						"fileName": "HourlySales.csv",
						"folderPath": "hourly",
						"fileSystem": "adfdemo"
					},
					"columnDelimiter": ",",
					"escapeChar": "\\",
					"firstRowAsHeader": true,
					"quoteChar": "\""
				},
				"schema": []
			},
			"dependsOn": [
				"[concat(variables('factoryId'), '/linkedServices/AzureDataLakeStorage1')]"
			]
		},
		{
			"name": "[concat(parameters('factoryName'), '/DailyFileDataset')]",
			"type": "Microsoft.DataFactory/factories/datasets",
			"apiVersion": "2018-06-01",
			"properties": {
				"linkedServiceName": {
					"referenceName": "AzureDataLakeStorage1",
					"type": "LinkedServiceReference"
				},
				"annotations": [],
				"type": "DelimitedText",
				"typeProperties": {
					"location": {
						"type": "AzureBlobFSLocation",
						"fileName": "DailySales.csv",
						"folderPath": "daily",
						"fileSystem": "adfdemo"
					},
					"columnDelimiter": ",",
					"escapeChar": "\\",
					"firstRowAsHeader": true,
					"quoteChar": "\""
				},
				"schema": []
			},
			"dependsOn": [
				"[concat(variables('factoryId'), '/linkedServices/AzureDataLakeStorage1')]"
			]
		},
		{
			"name": "[concat(parameters('factoryName'), '/DailyHourlySourceDataset')]",
			"type": "Microsoft.DataFactory/factories/datasets",
			"apiVersion": "2018-06-01",
			"properties": {
				"linkedServiceName": {
					"referenceName": "AzureDataLakeStorage1",
					"type": "LinkedServiceReference"
				},
				"annotations": [],
				"type": "DelimitedText",
				"typeProperties": {
					"location": {
						"type": "AzureBlobFSLocation",
						"fileName": "HourlySales.csv,DailySales.csv",
						"folderPath": "input",
						"fileSystem": "adfdemo"
					},
					"columnDelimiter": ",",
					"escapeChar": "\\",
					"firstRowAsHeader": true,
					"quoteChar": "\""
				},
				"schema": []
			},
			"dependsOn": [
				"[concat(variables('factoryId'), '/linkedServices/AzureDataLakeStorage1')]"
			]
		}
	]
}