{
	"$schema": "http://schema.management.azure.com/schemas/2015-01-01/deploymentTemplate.json#",
	"contentVersion": "1.0.0.0",
	"parameters": {
		"factoryName": {
			"type": "string",
			"metadata": "Data Factory name",
			"defaultValue": "VSADF2606"
		},
		"AzureDataLakeStorage242_properties_privateLinkResourceId": {
			"type": "string",
			"defaultValue": "/subscriptions/5e8b1b54-b36b-40df-8776-56bfad5e0633/resourceGroups/vijay_rg/providers/Microsoft.Storage/storageAccounts/storagevijaydemo"
		},
		"AzureDataLakeStorage242_properties_groupId": {
			"type": "string",
			"defaultValue": "dfs"
		}
	},
	"variables": {
		"factoryId": "[concat('Microsoft.DataFactory/factories/', parameters('factoryName'))]"
	},
	"resources": [
		{
			"name": "[concat(parameters('factoryName'), '/CdcAzSqlCountries')]",
			"type": "Microsoft.DataFactory/factories/adfcdcs",
			"apiVersion": "2018-06-01",
			"properties": {
				"SourceConnectionsInfo": [
					{
						"SourceEntities": [
							{
								"name": "dbo.Countries",
								"properties": {
									"schema": [
										{
											"name": "Id",
											"dataType": "integer"
										},
										{
											"name": "Countries",
											"dataType": "string"
										}
									],
									"dslConnectorProperties": [
										{
											"name": "schemaName",
											"value": "dbo"
										},
										{
											"name": "tableName",
											"value": "Countries"
										},
										{
											"name": "enableNativeCdc",
											"value": true
										},
										{
											"name": "netChanges",
											"value": true
										},
										{
											"name": "allowSchemaDrift",
											"value": false
										},
										{
											"name": "inferDriftedColumnTypes",
											"value": false
										}
									]
								}
							}
						],
						"Connection": {
							"linkedService": {
								"referenceName": "AzureSqlDatabasels",
								"type": "LinkedServiceReference"
							},
							"linkedServiceType": "AzureSqlDatabase",
							"type": "linkedservicetype",
							"isInlineDataset": true,
							"commonDslConnectorProperties": [
								{
									"name": "allowSchemaDrift",
									"value": true
								},
								{
									"name": "inferDriftedColumnTypes",
									"value": true
								},
								{
									"name": "format",
									"value": "table"
								},
								{
									"name": "store",
									"value": "sqlserver"
								},
								{
									"name": "databaseType",
									"value": "databaseType"
								},
								{
									"name": "database",
									"value": "database"
								},
								{
									"name": "skipInitialLoad",
									"value": true
								}
							]
						}
					}
				],
				"TargetConnectionsInfo": [
					{
						"TargetEntities": [
							{
								"name": "dbo.CountriesDW",
								"properties": {
									"schema": [
										{
											"name": "Id",
											"dataType": "integer"
										},
										{
											"name": "Countries",
											"dataType": "string"
										}
									],
									"dslConnectorProperties": [
										{
											"name": "schemaName",
											"value": "dbo"
										},
										{
											"name": "tableName",
											"value": "CountriesDW"
										},
										{
											"name": "allowSchemaDrift",
											"value": false
										},
										{
											"name": "inferDriftedColumnTypes",
											"value": false
										},
										{
											"name": "deletable",
											"value": true
										},
										{
											"name": "updateable",
											"value": true
										},
										{
											"name": "upsertable",
											"value": true
										},
										{
											"name": "defaultToUpsert",
											"value": true
										},
										{
											"name": "keys",
											"value": [
												"Id"
											]
										}
									]
								}
							}
						],
						"Connection": {
							"linkedService": {
								"referenceName": "AzureSqlDatabasels",
								"type": "LinkedServiceReference"
							},
							"linkedServiceType": "AzureSqlDatabase",
							"type": "linkedservicetype",
							"isInlineDataset": true,
							"commonDslConnectorProperties": [
								{
									"name": "allowSchemaDrift",
									"value": true
								},
								{
									"name": "inferDriftedColumnTypes",
									"value": true
								},
								{
									"name": "format",
									"value": "table"
								},
								{
									"name": "store",
									"value": "sqlserver"
								},
								{
									"name": "databaseType",
									"value": "databaseType"
								},
								{
									"name": "database",
									"value": "database"
								},
								{
									"name": "deletable",
									"value": false
								},
								{
									"name": "insertable",
									"value": true
								},
								{
									"name": "updateable",
									"value": false
								},
								{
									"name": "upsertable",
									"value": false
								},
								{
									"name": "skipDuplicateMapInputs",
									"value": true
								},
								{
									"name": "skipDuplicateMapOutputs",
									"value": true
								}
							]
						},
						"DataMapperMappings": [
							{
								"targetEntityName": "dbo.CountriesDW",
								"sourceEntityName": "dbo.Countries",
								"sourceConnectionReference": {
									"connectionName": "AzureSqlDatabasels",
									"type": "linkedservicetype"
								},
								"attributeMappingInfo": {
									"attributeMappings": [
										{
											"name": "Countries",
											"type": "Derived",
											"functionName": "upper",
											"expression": "upper(Countries)",
											"attributeReferences": [
												{
													"name": "Countries",
													"entity": "dbo.Countries",
													"entityConnectionReference": {
														"connectionName": "AzureSqlDatabasels",
														"type": "linkedservicetype"
													}
												}
											]
										},
										{
											"name": "Id",
											"type": "Direct",
											"functionName": "",
											"attributeReference": {
												"name": "Id",
												"entity": "dbo.Countries",
												"entityConnectionReference": {
													"connectionName": "AzureSqlDatabasels",
													"type": "linkedservicetype"
												}
											}
										}
									]
								}
							}
						],
						"Relationships": []
					}
				],
				"Policy": {
					"recurrence": {
						"frequency": "Minute",
						"interval": 1
					},
					"mode": "Microbatch"
				},
				"status": "Started",
				"allowVNetOverride": false
			},
			"dependsOn": []
		},
		{
			"name": "[concat(parameters('factoryName'), '/default/AzureDataLakeStorage242')]",
			"type": "Microsoft.DataFactory/factories/managedVirtualNetworks/managedPrivateEndpoints",
			"apiVersion": "2018-06-01",
			"properties": {
				"privateLinkResourceId": "[parameters('AzureDataLakeStorage242_properties_privateLinkResourceId')]",
				"groupId": "[parameters('AzureDataLakeStorage242_properties_groupId')]"
			},
			"dependsOn": []
		},
		{
			"name": "[concat(parameters('factoryName'), '/Delete_Activity')]",
			"type": "Microsoft.DataFactory/factories/pipelines",
			"apiVersion": "2018-06-01",
			"properties": {
				"activities": [
					{
						"name": "Delete1",
						"type": "Delete",
						"dependsOn": [],
						"policy": {
							"timeout": "0.12:00:00",
							"retry": 0,
							"retryIntervalInSeconds": 30,
							"secureOutput": false,
							"secureInput": false
						},
						"userProperties": [],
						"typeProperties": {
							"dataset": {
								"referenceName": "Output_CSV_DataSet_data_csv",
								"type": "DatasetReference",
								"parameters": {}
							},
							"logStorageSettings": {
								"linkedServiceName": {
									"referenceName": "AzureDataLakeStorage1",
									"type": "LinkedServiceReference"
								},
								"path": "adfdemo/errorlog"
							},
							"enableLogging": true,
							"storeSettings": {
								"type": "AzureBlobFSReadSettings",
								"recursive": true,
								"wildcardFileName": "*.csv",
								"enablePartitionDiscovery": false
							}
						}
					}
				],
				"policy": {
					"elapsedTimeMetric": {}
				},
				"annotations": []
			},
			"dependsOn": []
		},
		{
			"name": "[concat(parameters('factoryName'), '/Event Base Triggers Demo')]",
			"type": "Microsoft.DataFactory/factories/pipelines",
			"apiVersion": "2018-06-01",
			"properties": {
				"activities": [
					{
						"name": "Copy data1",
						"type": "Copy",
						"dependsOn": [],
						"policy": {
							"timeout": "0.12:00:00",
							"retry": 0,
							"retryIntervalInSeconds": 30,
							"secureOutput": false,
							"secureInput": false
						},
						"userProperties": [],
						"typeProperties": {
							"source": {
								"type": "DelimitedTextSource",
								"storeSettings": {
									"type": "AzureBlobFSReadSettings",
									"recursive": true,
									"enablePartitionDiscovery": false
								},
								"formatSettings": {
									"type": "DelimitedTextReadSettings"
								}
							},
							"sink": {
								"type": "DelimitedTextSink",
								"storeSettings": {
									"type": "AzureBlobFSWriteSettings",
									"copyBehavior": "PreserveHierarchy"
								},
								"formatSettings": {
									"type": "DelimitedTextWriteSettings",
									"quoteAllText": true,
									"fileExtension": ".txt"
								}
							},
							"enableStaging": false,
							"translator": {
								"type": "TabularTranslator",
								"typeConversion": true,
								"typeConversionSettings": {
									"allowDataTruncation": true,
									"treatBooleanAsNumber": false
								}
							}
						},
						"inputs": [
							{
								"referenceName": "Input_CSV_DataSet_data_csv",
								"type": "DatasetReference",
								"parameters": {}
							}
						],
						"outputs": [
							{
								"referenceName": "Output_CSV_DataSet_data_csv",
								"type": "DatasetReference",
								"parameters": {}
							}
						]
					}
				],
				"policy": {
					"elapsedTimeMetric": {}
				},
				"parameters": {
					"SourcePath": {
						"type": "string"
					},
					"SourceFile": {
						"type": "string"
					}
				},
				"annotations": [],
				"lastPublishTime": "2026-06-26T11:11:25Z"
			},
			"dependsOn": []
		},
		{
			"name": "[concat(parameters('factoryName'), '/ForEach_Activity_Demo')]",
			"type": "Microsoft.DataFactory/factories/pipelines",
			"apiVersion": "2018-06-01",
			"properties": {
				"activities": [
					{
						"name": "ForEach1",
						"type": "ForEach",
						"dependsOn": [],
						"userProperties": [],
						"typeProperties": {
							"items": {
								"value": "@pipeline().parameters.OutputLocations",
								"type": "Expression"
							},
							"isSequential": true,
							"activities": [
								{
									"name": "Copy data1",
									"type": "Copy",
									"dependsOn": [],
									"policy": {
										"timeout": "0.12:00:00",
										"retry": 0,
										"retryIntervalInSeconds": 30,
										"secureOutput": false,
										"secureInput": false
									},
									"userProperties": [],
									"typeProperties": {
										"source": {
											"type": "DelimitedTextSource",
											"storeSettings": {
												"type": "AzureBlobFSReadSettings",
												"recursive": true,
												"enablePartitionDiscovery": false
											},
											"formatSettings": {
												"type": "DelimitedTextReadSettings"
											}
										},
										"sink": {
											"type": "DelimitedTextSink",
											"storeSettings": {
												"type": "AzureBlobFSWriteSettings"
											},
											"formatSettings": {
												"type": "DelimitedTextWriteSettings",
												"quoteAllText": true,
												"fileExtension": ".txt"
											}
										},
										"enableStaging": false,
										"translator": {
											"type": "TabularTranslator",
											"typeConversion": true,
											"typeConversionSettings": {
												"allowDataTruncation": true,
												"treatBooleanAsNumber": false
											}
										}
									},
									"inputs": [
										{
											"referenceName": "Input_CSV_DataSet_data_csv",
											"type": "DatasetReference",
											"parameters": {}
										}
									],
									"outputs": [
										{
											"referenceName": "ForEachLoopDataset",
											"type": "DatasetReference",
											"parameters": {
												"OutputFolder": {
													"value": "@item()",
													"type": "Expression"
												}
											}
										}
									]
								}
							]
						}
					}
				],
				"policy": {
					"elapsedTimeMetric": {}
				},
				"parameters": {
					"OutputLocations": {
						"type": "array",
						"defaultValue": [
							"output1",
							"output2",
							"output3"
						]
					}
				},
				"annotations": []
			},
			"dependsOn": []
		},
		{
			"name": "[concat(parameters('factoryName'), '/GlobalParametersPipeline')]",
			"type": "Microsoft.DataFactory/factories/pipelines",
			"apiVersion": "2018-06-01",
			"properties": {
				"activities": [
					{
						"name": "Copy data1",
						"type": "Copy",
						"dependsOn": [],
						"policy": {
							"timeout": "0.12:00:00",
							"retry": 0,
							"retryIntervalInSeconds": 30,
							"secureOutput": false,
							"secureInput": false
						},
						"userProperties": [],
						"typeProperties": {
							"source": {
								"type": "DelimitedTextSource",
								"storeSettings": {
									"type": "AzureBlobFSReadSettings",
									"recursive": true,
									"enablePartitionDiscovery": false
								},
								"formatSettings": {
									"type": "DelimitedTextReadSettings"
								}
							},
							"sink": {
								"type": "DelimitedTextSink",
								"storeSettings": {
									"type": "AzureBlobFSWriteSettings"
								},
								"formatSettings": {
									"type": "DelimitedTextWriteSettings",
									"quoteAllText": true,
									"fileExtension": ".txt"
								}
							},
							"enableStaging": false,
							"translator": {
								"type": "TabularTranslator",
								"typeConversion": true,
								"typeConversionSettings": {
									"allowDataTruncation": true,
									"treatBooleanAsNumber": false
								}
							}
						},
						"inputs": [
							{
								"referenceName": "GlobalParameterDataset",
								"type": "DatasetReference",
								"parameters": {
									"Root": {
										"value": "@pipeline().globalParameters.GlobalSourceLocation",
										"type": "Expression"
									},
									"FileName": {
										"value": "@pipeline().parameters.FileName",
										"type": "Expression"
									}
								}
							}
						],
						"outputs": [
							{
								"referenceName": "GlobalParameterDataset",
								"type": "DatasetReference",
								"parameters": {
									"Root": {
										"value": "@pipeline().globalParameters.GlobalDestinationLocation",
										"type": "Expression"
									},
									"FileName": {
										"value": "@pipeline().parameters.FileName",
										"type": "Expression"
									}
								}
							}
						]
					}
				],
				"policy": {
					"elapsedTimeMetric": {}
				},
				"parameters": {
					"FileName": {
						"type": "string",
						"defaultValue": "cache_output_activity_source.csv"
					}
				},
				"annotations": []
			},
			"dependsOn": []
		},
		{
			"name": "[concat(parameters('factoryName'), '/If_Condition_Activity')]",
			"type": "Microsoft.DataFactory/factories/pipelines",
			"apiVersion": "2018-06-01",
			"properties": {
				"activities": [
					{
						"name": "If Condition1",
						"type": "IfCondition",
						"dependsOn": [],
						"userProperties": [],
						"typeProperties": {
							"expression": {
								"value": "@pipeline().parameters.If_Condition",
								"type": "Expression"
							},
							"ifFalseActivities": [
								{
									"name": "Copy data2",
									"type": "Copy",
									"dependsOn": [],
									"policy": {
										"timeout": "0.12:00:00",
										"retry": 0,
										"retryIntervalInSeconds": 30,
										"secureOutput": false,
										"secureInput": false
									},
									"userProperties": [],
									"typeProperties": {
										"source": {
											"type": "DelimitedTextSource",
											"storeSettings": {
												"type": "AzureBlobFSReadSettings",
												"recursive": true,
												"enablePartitionDiscovery": false
											},
											"formatSettings": {
												"type": "DelimitedTextReadSettings"
											}
										},
										"sink": {
											"type": "DelimitedTextSink",
											"storeSettings": {
												"type": "AzureBlobFSWriteSettings"
											},
											"formatSettings": {
												"type": "DelimitedTextWriteSettings",
												"quoteAllText": true,
												"fileExtension": ".txt"
											}
										},
										"enableStaging": false,
										"translator": {
											"type": "TabularTranslator",
											"typeConversion": true,
											"typeConversionSettings": {
												"allowDataTruncation": true,
												"treatBooleanAsNumber": false
											}
										}
									},
									"inputs": [
										{
											"referenceName": "Input_CSV_DataSet_data_csv",
											"type": "DatasetReference",
											"parameters": {}
										}
									],
									"outputs": [
										{
											"referenceName": "ForEachLoopDataset",
											"type": "DatasetReference",
											"parameters": {
												"OutputFolder": {
													"value": "@pipeline().parameters.OutputFolder",
													"type": "Expression"
												}
											}
										}
									]
								}
							],
							"ifTrueActivities": [
								{
									"name": "Copy data1",
									"type": "Copy",
									"dependsOn": [],
									"policy": {
										"timeout": "0.12:00:00",
										"retry": 0,
										"retryIntervalInSeconds": 30,
										"secureOutput": false,
										"secureInput": false
									},
									"userProperties": [],
									"typeProperties": {
										"source": {
											"type": "DelimitedTextSource",
											"storeSettings": {
												"type": "AzureBlobFSReadSettings",
												"recursive": true,
												"enablePartitionDiscovery": false
											},
											"formatSettings": {
												"type": "DelimitedTextReadSettings"
											}
										},
										"sink": {
											"type": "DelimitedTextSink",
											"storeSettings": {
												"type": "AzureBlobFSWriteSettings"
											},
											"formatSettings": {
												"type": "DelimitedTextWriteSettings",
												"quoteAllText": true,
												"fileExtension": ".txt"
											}
										},
										"enableStaging": false,
										"translator": {
											"type": "TabularTranslator",
											"typeConversion": true,
											"typeConversionSettings": {
												"allowDataTruncation": true,
												"treatBooleanAsNumber": false
											}
										}
									},
									"inputs": [
										{
											"referenceName": "Input_CSV_DataSet_data_csv",
											"type": "DatasetReference",
											"parameters": {}
										}
									],
									"outputs": [
										{
											"referenceName": "Output_CSV_DataSet_data_csv",
											"type": "DatasetReference",
											"parameters": {}
										}
									]
								}
							]
						}
					}
				],
				"policy": {
					"elapsedTimeMetric": {}
				},
				"parameters": {
					"If_Condition": {
						"type": "bool",
						"defaultValue": false
					},
					"OutputFolder": {
						"type": "string",
						"defaultValue": "output2"
					}
				},
				"annotations": []
			},
			"dependsOn": []
		},
		{
			"name": "[concat(parameters('factoryName'), '/Inline_Dataset_DataFlow_Pipeline')]",
			"type": "Microsoft.DataFactory/factories/pipelines",
			"apiVersion": "2018-06-01",
			"properties": {
				"activities": [
					{
						"name": "Data flow1",
						"type": "ExecuteDataFlow",
						"dependsOn": [],
						"policy": {
							"timeout": "0.12:00:00",
							"retry": 0,
							"retryIntervalInSeconds": 30,
							"secureOutput": false,
							"secureInput": false
						},
						"userProperties": [],
						"typeProperties": {
							"dataflow": {
								"referenceName": "InlineDatasetDataflow",
								"type": "DataFlowReference",
								"parameters": {},
								"datasetParameters": {
									"source1": {},
									"sink1": {}
								}
							},
							"staging": {},
							"compute": {
								"coreCount": 8,
								"computeType": "General"
							},
							"traceLevel": "Fine"
						}
					}
				],
				"policy": {
					"elapsedTimeMetric": {}
				},
				"annotations": []
			},
			"dependsOn": []
		},
		{
			"name": "[concat(parameters('factoryName'), '/Mapping_Copy_Activity_With_Settings')]",
			"type": "Microsoft.DataFactory/factories/pipelines",
			"apiVersion": "2018-06-01",
			"properties": {
				"activities": [
					{
						"name": "Copy data1",
						"type": "Copy",
						"dependsOn": [],
						"policy": {
							"timeout": "0.12:00:00",
							"retry": 0,
							"retryIntervalInSeconds": 30,
							"secureOutput": false,
							"secureInput": false
						},
						"userProperties": [
							{
								"name": "Source",
								"value": "adfdemo/input/data.csv"
							},
							{
								"name": "Target",
								"value": "adfdemo/output/data.csv"
							}
						],
						"typeProperties": {
							"source": {
								"type": "DelimitedTextSource",
								"storeSettings": {
									"type": "AzureBlobFSReadSettings",
									"recursive": true,
									"enablePartitionDiscovery": false
								},
								"formatSettings": {
									"type": "DelimitedTextReadSettings"
								}
							},
							"sink": {
								"type": "DelimitedTextSink",
								"storeSettings": {
									"type": "AzureBlobFSWriteSettings",
									"copyBehavior": "PreserveHierarchy"
								},
								"formatSettings": {
									"type": "DelimitedTextWriteSettings",
									"quoteAllText": true,
									"fileExtension": ".txt"
								}
							},
							"enableStaging": false,
							"logSettings": {
								"enableCopyActivityLog": true,
								"copyActivityLogSettings": {
									"logLevel": "Info",
									"enableReliableLogging": false
								},
								"logLocationSettings": {
									"linkedServiceName": {
										"referenceName": "AzureDataLakeStorage1",
										"type": "LinkedServiceReference"
									},
									"path": "adfdemo/errorlog/"
								}
							},
							"translator": {
								"type": "TabularTranslator",
								"mappings": [
									{
										"source": {
											"name": "emp_name",
											"type": "String",
											"physicalType": "String"
										},
										"sink": {
											"name": "emp_name",
											"type": "String",
											"physicalType": "String"
										}
									},
									{
										"source": {
											"name": "salary",
											"type": "String",
											"physicalType": "String"
										},
										"sink": {
											"name": "salary",
											"type": "String",
											"physicalType": "String"
										}
									},
									{
										"source": {
											"name": "emp_id",
											"type": "String",
											"physicalType": "String"
										},
										"sink": {
											"name": "emp_id",
											"type": "String",
											"physicalType": "String"
										}
									}
								],
								"typeConversion": true,
								"typeConversionSettings": {
									"allowDataTruncation": true,
									"treatBooleanAsNumber": false
								}
							}
						},
						"inputs": [
							{
								"referenceName": "Input_CSV_DataSet_data_csv",
								"type": "DatasetReference",
								"parameters": {}
							}
						],
						"outputs": [
							{
								"referenceName": "Output_CSV_DataSet_data_csv",
								"type": "DatasetReference",
								"parameters": {}
							}
						]
					}
				],
				"policy": {
					"elapsedTimeMetric": {}
				},
				"annotations": []
			},
			"dependsOn": []
		},
		{
			"name": "[concat(parameters('factoryName'), '/MetaData_Activity')]",
			"type": "Microsoft.DataFactory/factories/pipelines",
			"apiVersion": "2018-06-01",
			"properties": {
				"activities": [
					{
						"name": "Get Metadata1",
						"type": "GetMetadata",
						"dependsOn": [],
						"policy": {
							"timeout": "0.12:00:00",
							"retry": 0,
							"retryIntervalInSeconds": 30,
							"secureOutput": false,
							"secureInput": false
						},
						"userProperties": [],
						"typeProperties": {
							"dataset": {
								"referenceName": "Input_CSV_DataSet_data_csv",
								"type": "DatasetReference",
								"parameters": {}
							},
							"fieldList": [
								"lastModified"
							],
							"storeSettings": {
								"type": "AzureBlobFSReadSettings",
								"recursive": true,
								"enablePartitionDiscovery": false
							},
							"formatSettings": {
								"type": "DelimitedTextReadSettings"
							}
						}
					},
					{
						"name": "If Condition1",
						"type": "IfCondition",
						"dependsOn": [
							{
								"activity": "Get Metadata1",
								"dependencyConditions": [
									"Completed"
								]
							}
						],
						"userProperties": [
							{
								"name": "DateTime",
								"value": "formatDateTime(activity('Get Metadata1').output.lastModified,'yyyy-MM-dd')"
							}
						],
						"typeProperties": {
							"expression": {
								"value": "@equals(\n    formatDateTime(utcNow(),'yyyy-MM-dd'),\n    formatDateTime(activity('Get Metadata1').output.lastModified,'yyyy-MM-dd')\n )",
								"type": "Expression"
							},
							"ifFalseActivities": [
								{
									"name": "Copy data2",
									"type": "Copy",
									"dependsOn": [],
									"policy": {
										"timeout": "0.12:00:00",
										"retry": 0,
										"retryIntervalInSeconds": 30,
										"secureOutput": false,
										"secureInput": false
									},
									"userProperties": [],
									"typeProperties": {
										"source": {
											"type": "DelimitedTextSource",
											"storeSettings": {
												"type": "AzureBlobFSReadSettings",
												"recursive": true,
												"enablePartitionDiscovery": false
											},
											"formatSettings": {
												"type": "DelimitedTextReadSettings"
											}
										},
										"sink": {
											"type": "DelimitedTextSink",
											"storeSettings": {
												"type": "AzureBlobFSWriteSettings"
											},
											"formatSettings": {
												"type": "DelimitedTextWriteSettings",
												"quoteAllText": true,
												"fileExtension": ".txt"
											}
										},
										"enableStaging": false,
										"translator": {
											"type": "TabularTranslator",
											"typeConversion": true,
											"typeConversionSettings": {
												"allowDataTruncation": true,
												"treatBooleanAsNumber": false
											}
										}
									},
									"inputs": [
										{
											"referenceName": "Input_CSV_DataSet_data_csv",
											"type": "DatasetReference",
											"parameters": {}
										}
									],
									"outputs": [
										{
											"referenceName": "Output_CSV_DataSet_data_csv",
											"type": "DatasetReference",
											"parameters": {}
										}
									]
								}
							],
							"ifTrueActivities": [
								{
									"name": "Copy data1",
									"type": "Copy",
									"dependsOn": [],
									"policy": {
										"timeout": "0.12:00:00",
										"retry": 0,
										"retryIntervalInSeconds": 30,
										"secureOutput": false,
										"secureInput": false
									},
									"userProperties": [],
									"typeProperties": {
										"source": {
											"type": "DelimitedTextSource",
											"storeSettings": {
												"type": "AzureBlobFSReadSettings",
												"recursive": true,
												"enablePartitionDiscovery": false
											},
											"formatSettings": {
												"type": "DelimitedTextReadSettings"
											}
										},
										"sink": {
											"type": "DelimitedTextSink",
											"storeSettings": {
												"type": "AzureBlobFSWriteSettings"
											},
											"formatSettings": {
												"type": "DelimitedTextWriteSettings",
												"quoteAllText": true,
												"fileExtension": ".txt"
											}
										},
										"enableStaging": false,
										"translator": {
											"type": "TabularTranslator",
											"typeConversion": true,
											"typeConversionSettings": {
												"allowDataTruncation": true,
												"treatBooleanAsNumber": false
											}
										}
									},
									"inputs": [
										{
											"referenceName": "Input_CSV_DataSet_data_csv",
											"type": "DatasetReference",
											"parameters": {}
										}
									],
									"outputs": [
										{
											"referenceName": "Output_CSV_DataSet_data_csv",
											"type": "DatasetReference",
											"parameters": {}
										}
									]
								}
							]
						}
					}
				],
				"policy": {
					"elapsedTimeMetric": {}
				},
				"annotations": []
			},
			"dependsOn": []
		},
		{
			"name": "[concat(parameters('factoryName'), '/Pagination_Dynamic_Offset_Implementation_Pipeline')]",
			"type": "Microsoft.DataFactory/factories/pipelines",
			"apiVersion": "2018-06-01",
			"properties": {
				"activities": [
					{
						"name": "Copy data1",
						"type": "Copy",
						"dependsOn": [],
						"policy": {
							"timeout": "0.12:00:00",
							"retry": 0,
							"retryIntervalInSeconds": 30,
							"secureOutput": false,
							"secureInput": false
						},
						"userProperties": [],
						"typeProperties": {
							"source": {
								"type": "RestSource",
								"httpRequestTimeout": "00:01:40",
								"requestInterval": "00.00:00:00.010",
								"requestMethod": "GET",
								"paginationRules": {
									"QueryParameters.{offset}": "RANGE:0:1351:20"
								}
							},
							"sink": {
								"type": "DelimitedTextSink",
								"storeSettings": {
									"type": "AzureBlobFSWriteSettings",
									"copyBehavior": "PreserveHierarchy"
								},
								"formatSettings": {
									"type": "DelimitedTextWriteSettings",
									"quoteAllText": true,
									"fileExtension": ".csv"
								}
							},
							"enableStaging": false,
							"translator": {
								"type": "TabularTranslator",
								"mappings": [
									{
										"source": {
											"path": "[['name']"
										},
										"sink": {
											"name": "name"
										}
									},
									{
										"source": {
											"path": "[['url']"
										},
										"sink": {
											"name": "url"
										}
									}
								],
								"collectionReference": "$['results']"
							}
						},
						"inputs": [
							{
								"referenceName": "RestResourceDynamicOffsetDataset",
								"type": "DatasetReference",
								"parameters": {}
							}
						],
						"outputs": [
							{
								"referenceName": "Pagination_Implementation_Dataset",
								"type": "DatasetReference",
								"parameters": {}
							}
						]
					}
				],
				"policy": {
					"elapsedTimeMetric": {}
				},
				"annotations": []
			},
			"dependsOn": []
		},
		{
			"name": "[concat(parameters('factoryName'), '/Pagination_Implementation_Pipeline')]",
			"type": "Microsoft.DataFactory/factories/pipelines",
			"apiVersion": "2018-06-01",
			"properties": {
				"activities": [
					{
						"name": "Copy data1",
						"type": "Copy",
						"dependsOn": [],
						"policy": {
							"timeout": "0.12:00:00",
							"retry": 0,
							"retryIntervalInSeconds": 30,
							"secureOutput": false,
							"secureInput": false
						},
						"userProperties": [],
						"typeProperties": {
							"source": {
								"type": "RestSource",
								"httpRequestTimeout": "00:01:40",
								"requestInterval": "00.00:00:00.010",
								"requestMethod": "GET",
								"paginationRules": {
									"AbsoluteUrl": "$.next"
								}
							},
							"sink": {
								"type": "DelimitedTextSink",
								"storeSettings": {
									"type": "AzureBlobFSWriteSettings",
									"copyBehavior": "PreserveHierarchy"
								},
								"formatSettings": {
									"type": "DelimitedTextWriteSettings",
									"quoteAllText": true,
									"fileExtension": ".csv"
								}
							},
							"enableStaging": false,
							"translator": {
								"type": "TabularTranslator",
								"mappings": [
									{
										"source": {
											"path": "[['name']"
										},
										"sink": {
											"name": "name"
										}
									},
									{
										"source": {
											"path": "[['url']"
										},
										"sink": {
											"name": "url"
										}
									}
								],
								"collectionReference": "$['results']"
							}
						},
						"inputs": [
							{
								"referenceName": "RestResourceDataset",
								"type": "DatasetReference",
								"parameters": {}
							}
						],
						"outputs": [
							{
								"referenceName": "Pagination_Implementation_Dataset",
								"type": "DatasetReference",
								"parameters": {}
							}
						]
					}
				],
				"policy": {
					"elapsedTimeMetric": {}
				},
				"annotations": []
			},
			"dependsOn": []
		},
		{
			"name": "[concat(parameters('factoryName'), '/Parameterized_Pipeline_Demo')]",
			"type": "Microsoft.DataFactory/factories/pipelines",
			"apiVersion": "2018-06-01",
			"properties": {
				"activities": [
					{
						"name": "Copy data1",
						"type": "Copy",
						"dependsOn": [],
						"policy": {
							"timeout": "0.12:00:00",
							"retry": 0,
							"retryIntervalInSeconds": 30,
							"secureOutput": false,
							"secureInput": false
						},
						"userProperties": [],
						"typeProperties": {
							"source": {
								"type": "SqlServerSource",
								"queryTimeout": "02:00:00",
								"partitionOption": "None"
							},
							"sink": {
								"type": "SqlServerSink",
								"writeBehavior": "insert",
								"sqlWriterUseTableLock": false
							},
							"enableStaging": false,
							"translator": {
								"type": "TabularTranslator",
								"typeConversion": true,
								"typeConversionSettings": {
									"allowDataTruncation": true,
									"treatBooleanAsNumber": false
								}
							}
						},
						"inputs": [
							{
								"referenceName": "ParamSqlServerTable",
								"type": "DatasetReference",
								"parameters": {
									"datasetServer": {
										"value": "@pipeline().parameters.serverNameFromPipeline",
										"type": "Expression"
									},
									"datasetDb": {
										"value": "@pipeline().parameters.dbNameFromPipeline",
										"type": "Expression"
									},
									"datasetUserName": {
										"value": "@pipeline().parameters.userNameFromPipeline",
										"type": "Expression"
									},
									"datasetPassword": {
										"value": "@pipeline().parameters.passwordNameFromPipeline",
										"type": "Expression"
									},
									"datasetDbo": {
										"value": "@pipeline().parameters.dboNameFromPipeline",
										"type": "Expression"
									},
									"datasetTable": {
										"value": "@pipeline().parameters.sourceTableNameFromPipeline",
										"type": "Expression"
									}
								}
							}
						],
						"outputs": [
							{
								"referenceName": "ParamSqlServerTable",
								"type": "DatasetReference",
								"parameters": {
									"datasetServer": {
										"value": "@pipeline().parameters.serverNameFromPipeline",
										"type": "Expression"
									},
									"datasetDb": {
										"value": "@pipeline().parameters.dbNameFromPipeline",
										"type": "Expression"
									},
									"datasetUserName": {
										"value": "@pipeline().parameters.userNameFromPipeline",
										"type": "Expression"
									},
									"datasetPassword": {
										"value": "@pipeline().parameters.passwordNameFromPipeline",
										"type": "Expression"
									},
									"datasetDbo": {
										"value": "@pipeline().parameters.dboNameFromPipeline",
										"type": "Expression"
									},
									"datasetTable": {
										"value": "@pipeline().parameters.destinationTableNameFromPipeline",
										"type": "Expression"
									}
								}
							}
						]
					}
				],
				"policy": {
					"elapsedTimeMetric": {}
				},
				"parameters": {
					"serverNameFromPipeline": {
						"type": "string"
					},
					"dbNameFromPipeline": {
						"type": "string"
					},
					"passwordNameFromPipeline": {
						"type": "string"
					},
					"userNameFromPipeline": {
						"type": "string"
					},
					"dboNameFromPipeline": {
						"type": "string"
					},
					"sourceTableNameFromPipeline": {
						"type": "string"
					},
					"destinationTableNameFromPipeline": {
						"type": "string"
					}
				},
				"annotations": []
			},
			"dependsOn": []
		},
		{
			"name": "[concat(parameters('factoryName'), '/Scenario2_Dynamically_Copying_Files')]",
			"type": "Microsoft.DataFactory/factories/pipelines",
			"apiVersion": "2018-06-01",
			"properties": {
				"activities": [
					{
						"name": "Get Metadata1",
						"type": "GetMetadata",
						"dependsOn": [],
						"policy": {
							"timeout": "0.12:00:00",
							"retry": 0,
							"retryIntervalInSeconds": 30,
							"secureOutput": false,
							"secureInput": false
						},
						"userProperties": [],
						"typeProperties": {
							"dataset": {
								"referenceName": "Scenario2MetaDataDataset",
								"type": "DatasetReference",
								"parameters": {}
							},
							"fieldList": [
								"childItems"
							],
							"storeSettings": {
								"type": "AzureBlobFSReadSettings",
								"recursive": true,
								"enablePartitionDiscovery": false
							},
							"formatSettings": {
								"type": "DelimitedTextReadSettings"
							}
						}
					},
					{
						"name": "ForEach1",
						"type": "ForEach",
						"dependsOn": [
							{
								"activity": "Get Metadata1",
								"dependencyConditions": [
									"Succeeded"
								]
							}
						],
						"userProperties": [],
						"typeProperties": {
							"items": {
								"value": "@activity('Get Metadata1').output.childItems",
								"type": "Expression"
							},
							"activities": [
								{
									"name": "Copy data1",
									"type": "Copy",
									"dependsOn": [],
									"policy": {
										"timeout": "0.12:00:00",
										"retry": 0,
										"retryIntervalInSeconds": 30,
										"secureOutput": false,
										"secureInput": false
									},
									"userProperties": [],
									"typeProperties": {
										"source": {
											"type": "DelimitedTextSource",
											"storeSettings": {
												"type": "AzureBlobFSReadSettings",
												"recursive": true,
												"enablePartitionDiscovery": false
											},
											"formatSettings": {
												"type": "DelimitedTextReadSettings"
											}
										},
										"sink": {
											"type": "DelimitedTextSink",
											"storeSettings": {
												"type": "AzureBlobFSWriteSettings"
											},
											"formatSettings": {
												"type": "DelimitedTextWriteSettings",
												"quoteAllText": true,
												"fileExtension": ".txt"
											}
										},
										"enableStaging": false,
										"translator": {
											"type": "TabularTranslator",
											"typeConversion": true,
											"typeConversionSettings": {
												"allowDataTruncation": true,
												"treatBooleanAsNumber": false
											}
										}
									},
									"inputs": [
										{
											"referenceName": "Scenario2SourceDataSet",
											"type": "DatasetReference",
											"parameters": {
												"fileName": {
													"value": "@item().name",
													"type": "Expression"
												}
											}
										}
									],
									"outputs": [
										{
											"referenceName": "Scenario2TargetDataSet",
											"type": "DatasetReference",
											"parameters": {
												"fileName": {
													"value": "@item().name",
													"type": "Expression"
												}
											}
										}
									]
								}
							]
						}
					}
				],
				"policy": {
					"elapsedTimeMetric": {}
				},
				"annotations": []
			},
			"dependsOn": []
		},
		{
			"name": "[concat(parameters('factoryName'), '/Scenario3_Incremently_Copy_New_FIles_Pipeline')]",
			"type": "Microsoft.DataFactory/factories/pipelines",
			"apiVersion": "2018-06-01",
			"properties": {
				"activities": [
					{
						"name": "Copy data1",
						"type": "Copy",
						"dependsOn": [],
						"policy": {
							"timeout": "0.12:00:00",
							"retry": 0,
							"retryIntervalInSeconds": 30,
							"secureOutput": false,
							"secureInput": false
						},
						"userProperties": [],
						"typeProperties": {
							"source": {
								"type": "DelimitedTextSource",
								"storeSettings": {
									"type": "AzureBlobFSReadSettings",
									"recursive": true,
									"modifiedDatetimeStart": {
										"value": "@adddays(utcNow(),-2)",
										"type": "Expression"
									},
									"modifiedDatetimeEnd": {
										"value": "@utcNow()",
										"type": "Expression"
									},
									"wildcardFolderPath": "input",
									"wildcardFileName": "*.csv",
									"enablePartitionDiscovery": false
								},
								"formatSettings": {
									"type": "DelimitedTextReadSettings"
								}
							},
							"sink": {
								"type": "DelimitedTextSink",
								"storeSettings": {
									"type": "AzureBlobFSWriteSettings"
								},
								"formatSettings": {
									"type": "DelimitedTextWriteSettings",
									"quoteAllText": true,
									"fileExtension": ".txt"
								}
							},
							"enableStaging": false,
							"translator": {
								"type": "TabularTranslator",
								"typeConversion": true,
								"typeConversionSettings": {
									"allowDataTruncation": true,
									"treatBooleanAsNumber": false
								}
							}
						},
						"inputs": [
							{
								"referenceName": "Scenario3_Source_Datatset",
								"type": "DatasetReference",
								"parameters": {}
							}
						],
						"outputs": [
							{
								"referenceName": "Scenario3_Target_Dataset",
								"type": "DatasetReference",
								"parameters": {}
							}
						]
					}
				],
				"policy": {
					"elapsedTimeMetric": {}
				},
				"annotations": []
			},
			"dependsOn": []
		},
		{
			"name": "[concat(parameters('factoryName'), '/Scenario4_Delete_Old_Files_Pipeline')]",
			"type": "Microsoft.DataFactory/factories/pipelines",
			"apiVersion": "2018-06-01",
			"properties": {
				"activities": [
					{
						"name": "Get Metadata1",
						"type": "GetMetadata",
						"dependsOn": [],
						"policy": {
							"timeout": "0.12:00:00",
							"retry": 0,
							"retryIntervalInSeconds": 30,
							"secureOutput": false,
							"secureInput": false
						},
						"userProperties": [],
						"typeProperties": {
							"dataset": {
								"referenceName": "Scenario4_Source_Dataset",
								"type": "DatasetReference",
								"parameters": {}
							},
							"fieldList": [
								"childItems"
							],
							"storeSettings": {
								"type": "AzureBlobFSReadSettings",
								"recursive": true,
								"modifiedDatetimeEnd": {
									"value": "@adddays(utcNow(),-14)",
									"type": "Expression"
								},
								"enablePartitionDiscovery": false
							},
							"formatSettings": {
								"type": "DelimitedTextReadSettings"
							}
						}
					},
					{
						"name": "ForEach1",
						"type": "ForEach",
						"dependsOn": [
							{
								"activity": "Get Metadata1",
								"dependencyConditions": [
									"Succeeded"
								]
							}
						],
						"userProperties": [],
						"typeProperties": {
							"items": {
								"value": "@activity('Get Metadata1').output.childItems",
								"type": "Expression"
							},
							"activities": [
								{
									"name": "Delete1",
									"type": "Delete",
									"dependsOn": [],
									"policy": {
										"timeout": "0.12:00:00",
										"retry": 0,
										"retryIntervalInSeconds": 30,
										"secureOutput": false,
										"secureInput": false
									},
									"userProperties": [],
									"typeProperties": {
										"dataset": {
											"referenceName": "Scenario3_Source_Datatset",
											"type": "DatasetReference",
											"parameters": {}
										},
										"logStorageSettings": {
											"linkedServiceName": {
												"referenceName": "AzureDataLakeStorage1",
												"type": "LinkedServiceReference"
											},
											"path": "adfdemo/input/logs"
										},
										"enableLogging": true,
										"storeSettings": {
											"type": "AzureBlobFSReadSettings",
											"recursive": true,
											"wildcardFileName": {
												"value": "@item().name",
												"type": "Expression"
											},
											"enablePartitionDiscovery": false
										}
									}
								}
							]
						}
					}
				],
				"policy": {
					"elapsedTimeMetric": {}
				},
				"annotations": []
			},
			"dependsOn": []
		},
		{
			"name": "[concat(parameters('factoryName'), '/Set_Variable_Pipeline')]",
			"type": "Microsoft.DataFactory/factories/pipelines",
			"apiVersion": "2018-06-01",
			"properties": {
				"activities": [
					{
						"name": "Set variable1",
						"type": "SetVariable",
						"dependsOn": [],
						"policy": {
							"secureOutput": false,
							"secureInput": false
						},
						"userProperties": [
							{
								"name": "FileType",
								"value": "@replace(pipeline().parameters.FileName,'Sales.csv','')"
							}
						],
						"typeProperties": {
							"variableName": "FileType",
							"value": {
								"value": "@replace(pipeline().parameters.FileName,'Sales.csv','')",
								"type": "Expression"
							}
						}
					},
					{
						"name": "If Condition1",
						"type": "IfCondition",
						"dependsOn": [
							{
								"activity": "Set variable1",
								"dependencyConditions": [
									"Succeeded"
								]
							}
						],
						"userProperties": [],
						"typeProperties": {
							"expression": {
								"value": "@equals(variables('FileType'),'Hourly')",
								"type": "Expression"
							},
							"ifFalseActivities": [
								{
									"name": "Copy data2",
									"type": "Copy",
									"dependsOn": [],
									"policy": {
										"timeout": "0.12:00:00",
										"retry": 0,
										"retryIntervalInSeconds": 30,
										"secureOutput": false,
										"secureInput": false
									},
									"userProperties": [],
									"typeProperties": {
										"source": {
											"type": "DelimitedTextSource",
											"storeSettings": {
												"type": "AzureBlobFSReadSettings",
												"recursive": true,
												"enablePartitionDiscovery": false
											},
											"formatSettings": {
												"type": "DelimitedTextReadSettings"
											}
										},
										"sink": {
											"type": "DelimitedTextSink",
											"storeSettings": {
												"type": "AzureBlobFSWriteSettings"
											},
											"formatSettings": {
												"type": "DelimitedTextWriteSettings",
												"quoteAllText": true,
												"fileExtension": ".txt"
											}
										},
										"enableStaging": false,
										"translator": {
											"type": "TabularTranslator",
											"typeConversion": true,
											"typeConversionSettings": {
												"allowDataTruncation": true,
												"treatBooleanAsNumber": false
											}
										}
									},
									"inputs": [
										{
											"referenceName": "DailySourceDataset",
											"type": "DatasetReference",
											"parameters": {}
										}
									],
									"outputs": [
										{
											"referenceName": "DailyFileDataset",
											"type": "DatasetReference",
											"parameters": {}
										}
									]
								}
							],
							"ifTrueActivities": [
								{
									"name": "Copy data1",
									"type": "Copy",
									"dependsOn": [],
									"policy": {
										"timeout": "0.12:00:00",
										"retry": 0,
										"retryIntervalInSeconds": 30,
										"secureOutput": false,
										"secureInput": false
									},
									"userProperties": [],
									"typeProperties": {
										"source": {
											"type": "DelimitedTextSource",
											"storeSettings": {
												"type": "AzureBlobFSReadSettings",
												"recursive": true,
												"enablePartitionDiscovery": false
											},
											"formatSettings": {
												"type": "DelimitedTextReadSettings"
											}
										},
										"sink": {
											"type": "DelimitedTextSink",
											"storeSettings": {
												"type": "AzureBlobFSWriteSettings"
											},
											"formatSettings": {
												"type": "DelimitedTextWriteSettings",
												"quoteAllText": true,
												"fileExtension": ".txt"
											}
										},
										"enableStaging": false,
										"translator": {
											"type": "TabularTranslator",
											"typeConversion": true,
											"typeConversionSettings": {
												"allowDataTruncation": true,
												"treatBooleanAsNumber": false
											}
										}
									},
									"inputs": [
										{
											"referenceName": "HourlySourceDataset",
											"type": "DatasetReference",
											"parameters": {}
										}
									],
									"outputs": [
										{
											"referenceName": "HourlyFileDataset",
											"type": "DatasetReference",
											"parameters": {}
										}
									]
								}
							]
						}
					}
				],
				"policy": {
					"elapsedTimeMetric": {}
				},
				"parameters": {
					"FileName": {
						"type": "string"
					}
				},
				"variables": {
					"FileType": {
						"type": "String"
					}
				},
				"annotations": []
			},
			"dependsOn": []
		},
		{
			"name": "[concat(parameters('factoryName'), '/Set_Variable_Return_Value_Child_Pipeline')]",
			"type": "Microsoft.DataFactory/factories/pipelines",
			"apiVersion": "2018-06-01",
			"properties": {
				"activities": [
					{
						"name": "Copy data1",
						"type": "Copy",
						"dependsOn": [],
						"policy": {
							"timeout": "0.12:00:00",
							"retry": 0,
							"retryIntervalInSeconds": 30,
							"secureOutput": false,
							"secureInput": false
						},
						"userProperties": [],
						"typeProperties": {
							"source": {
								"type": "DelimitedTextSource",
								"storeSettings": {
									"type": "AzureBlobFSReadSettings",
									"recursive": true,
									"enablePartitionDiscovery": false
								},
								"formatSettings": {
									"type": "DelimitedTextReadSettings"
								}
							},
							"sink": {
								"type": "DelimitedTextSink",
								"storeSettings": {
									"type": "AzureBlobFSWriteSettings"
								},
								"formatSettings": {
									"type": "DelimitedTextWriteSettings",
									"quoteAllText": true,
									"fileExtension": ".txt"
								}
							},
							"enableStaging": false,
							"translator": {
								"type": "TabularTranslator",
								"typeConversion": true,
								"typeConversionSettings": {
									"allowDataTruncation": true,
									"treatBooleanAsNumber": false
								}
							}
						},
						"inputs": [
							{
								"referenceName": "Hr_Employees_File_Dataset",
								"type": "DatasetReference",
								"parameters": {}
							}
						],
						"outputs": [
							{
								"referenceName": "ForEachLoopDataset",
								"type": "DatasetReference",
								"parameters": {}
							}
						]
					},
					{
						"name": "Set variable1",
						"type": "SetVariable",
						"dependsOn": [
							{
								"activity": "Copy data1",
								"dependencyConditions": [
									"Succeeded"
								]
							}
						],
						"policy": {
							"secureOutput": false,
							"secureInput": false
						},
						"userProperties": [],
						"typeProperties": {
							"variableName": "pipelineReturnValue",
							"value": [
								{
									"key": "pipelineName",
									"value": {
										"type": "Expression",
										"content": "@pipeline().Pipeline"
									}
								},
								{
									"key": "pipelineRunId",
									"value": {
										"type": "Expression",
										"content": "@pipeline().RunId"
									}
								}
							],
							"setSystemVariable": true
						}
					}
				],
				"policy": {
					"elapsedTimeMetric": {}
				},
				"annotations": []
			},
			"dependsOn": []
		},
		{
			"name": "[concat(parameters('factoryName'), '/Storage_Account_File_Movement')]",
			"type": "Microsoft.DataFactory/factories/pipelines",
			"apiVersion": "2018-06-01",
			"properties": {
				"activities": [
					{
						"name": "Copy data1",
						"type": "Copy",
						"dependsOn": [],
						"policy": {
							"timeout": "0.12:00:00",
							"retry": 0,
							"retryIntervalInSeconds": 30,
							"secureOutput": false,
							"secureInput": false
						},
						"userProperties": [],
						"typeProperties": {
							"source": {
								"type": "DelimitedTextSource",
								"storeSettings": {
									"type": "AzureBlobFSReadSettings",
									"recursive": true,
									"enablePartitionDiscovery": false
								},
								"formatSettings": {
									"type": "DelimitedTextReadSettings"
								}
							},
							"sink": {
								"type": "DelimitedTextSink",
								"storeSettings": {
									"type": "AzureBlobFSWriteSettings",
									"copyBehavior": "PreserveHierarchy"
								},
								"formatSettings": {
									"type": "DelimitedTextWriteSettings",
									"quoteAllText": true,
									"fileExtension": ".txt"
								}
							},
							"enableStaging": false,
							"translator": {
								"type": "TabularTranslator",
								"typeConversion": true,
								"typeConversionSettings": {
									"allowDataTruncation": true,
									"treatBooleanAsNumber": false
								}
							}
						},
						"inputs": [
							{
								"referenceName": "Input_CSV_DataSet_data_csv",
								"type": "DatasetReference",
								"parameters": {}
							}
						],
						"outputs": [
							{
								"referenceName": "Output_CSV_DataSet_data_csv",
								"type": "DatasetReference",
								"parameters": {}
							}
						]
					}
				],
				"policy": {
					"elapsedTimeMetric": {}
				},
				"annotations": [],
				"lastPublishTime": "2026-06-26T11:11:25Z"
			},
			"dependsOn": []
		},
		{
			"name": "[concat(parameters('factoryName'), '/Switch_Activity')]",
			"type": "Microsoft.DataFactory/factories/pipelines",
			"apiVersion": "2018-06-01",
			"properties": {
				"activities": [
					{
						"name": "Switch1",
						"type": "Switch",
						"dependsOn": [],
						"userProperties": [],
						"typeProperties": {
							"on": {
								"value": "@pipeline().parameters.FolderName",
								"type": "Expression"
							},
							"cases": [
								{
									"value": "output1",
									"activities": [
										{
											"name": "Copy data1",
											"type": "Copy",
											"dependsOn": [],
											"policy": {
												"timeout": "0.12:00:00",
												"retry": 0,
												"retryIntervalInSeconds": 30,
												"secureOutput": false,
												"secureInput": false
											},
											"userProperties": [],
											"typeProperties": {
												"source": {
													"type": "DelimitedTextSource",
													"storeSettings": {
														"type": "AzureBlobFSReadSettings",
														"recursive": true,
														"enablePartitionDiscovery": false
													},
													"formatSettings": {
														"type": "DelimitedTextReadSettings"
													}
												},
												"sink": {
													"type": "DelimitedTextSink",
													"storeSettings": {
														"type": "AzureBlobFSWriteSettings"
													},
													"formatSettings": {
														"type": "DelimitedTextWriteSettings",
														"quoteAllText": true,
														"fileExtension": ".txt"
													}
												},
												"enableStaging": false,
												"translator": {
													"type": "TabularTranslator",
													"typeConversion": true,
													"typeConversionSettings": {
														"allowDataTruncation": true,
														"treatBooleanAsNumber": false
													}
												}
											},
											"inputs": [
												{
													"referenceName": "Input_CSV_DataSet_data_csv",
													"type": "DatasetReference",
													"parameters": {}
												}
											],
											"outputs": [
												{
													"referenceName": "ForEachLoopDataset",
													"type": "DatasetReference",
													"parameters": {
														"OutputFolder": {
															"value": "@pipeline().parameters.FolderName",
															"type": "Expression"
														}
													}
												}
											]
										}
									]
								},
								{
									"value": "output2",
									"activities": [
										{
											"name": "Copy data2",
											"type": "Copy",
											"dependsOn": [],
											"policy": {
												"timeout": "0.12:00:00",
												"retry": 0,
												"retryIntervalInSeconds": 30,
												"secureOutput": false,
												"secureInput": false
											},
											"userProperties": [],
											"typeProperties": {
												"source": {
													"type": "DelimitedTextSource",
													"storeSettings": {
														"type": "AzureBlobFSReadSettings",
														"recursive": true,
														"enablePartitionDiscovery": false
													},
													"formatSettings": {
														"type": "DelimitedTextReadSettings"
													}
												},
												"sink": {
													"type": "DelimitedTextSink",
													"storeSettings": {
														"type": "AzureBlobFSWriteSettings"
													},
													"formatSettings": {
														"type": "DelimitedTextWriteSettings",
														"quoteAllText": true,
														"fileExtension": ".txt"
													}
												},
												"enableStaging": false,
												"translator": {
													"type": "TabularTranslator",
													"typeConversion": true,
													"typeConversionSettings": {
														"allowDataTruncation": true,
														"treatBooleanAsNumber": false
													}
												}
											},
											"inputs": [
												{
													"referenceName": "Input_CSV_DataSet_data_csv",
													"type": "DatasetReference",
													"parameters": {}
												}
											],
											"outputs": [
												{
													"referenceName": "ForEachLoopDataset",
													"type": "DatasetReference",
													"parameters": {
														"OutputFolder": {
															"value": "@pipeline().parameters.FolderName",
															"type": "Expression"
														}
													}
												}
											]
										}
									]
								}
							],
							"defaultActivities": [
								{
									"name": "Default Copy",
									"type": "Copy",
									"dependsOn": [],
									"policy": {
										"timeout": "0.12:00:00",
										"retry": 0,
										"retryIntervalInSeconds": 30,
										"secureOutput": false,
										"secureInput": false
									},
									"userProperties": [],
									"typeProperties": {
										"source": {
											"type": "DelimitedTextSource",
											"storeSettings": {
												"type": "AzureBlobFSReadSettings",
												"recursive": true,
												"enablePartitionDiscovery": false
											},
											"formatSettings": {
												"type": "DelimitedTextReadSettings"
											}
										},
										"sink": {
											"type": "DelimitedTextSink",
											"storeSettings": {
												"type": "AzureBlobFSWriteSettings"
											},
											"formatSettings": {
												"type": "DelimitedTextWriteSettings",
												"quoteAllText": true,
												"fileExtension": ".txt"
											}
										},
										"enableStaging": false,
										"translator": {
											"type": "TabularTranslator",
											"typeConversion": true,
											"typeConversionSettings": {
												"allowDataTruncation": true,
												"treatBooleanAsNumber": false
											}
										}
									},
									"inputs": [
										{
											"referenceName": "Input_CSV_DataSet_data_csv",
											"type": "DatasetReference",
											"parameters": {}
										}
									],
									"outputs": [
										{
											"referenceName": "ForEachLoopDataset",
											"type": "DatasetReference",
											"parameters": {
												"OutputFolder": {
													"value": "@pipeline().parameters.FolderName",
													"type": "Expression"
												}
											}
										}
									]
								}
							]
						}
					}
				],
				"policy": {
					"elapsedTimeMetric": {}
				},
				"parameters": {
					"FolderName": {
						"type": "string",
						"defaultValue": "output"
					}
				},
				"annotations": []
			},
			"dependsOn": []
		}
	]
}