{
	"$schema": "http://schema.management.azure.com/schemas/2015-01-01/deploymentTemplate.json#",
	"contentVersion": "1.0.0.0",
	"parameters": {
		"factoryName": {
			"type": "string",
			"metadata": "Data Factory name",
			"defaultValue": "VSADF2606"
		}
	},
	"variables": {
		"factoryId": "[concat('Microsoft.DataFactory/factories/', parameters('factoryName'))]"
	},
	"resources": [
		{
			"name": "[concat(parameters('factoryName'), '/Conditional_Split_Dataflow')]",
			"type": "Microsoft.DataFactory/factories/dataflows",
			"apiVersion": "2018-06-01",
			"properties": {
				"type": "MappingDataFlow",
				"typeProperties": {
					"sources": [
						{
							"dataset": {
								"referenceName": "DelimitedText1",
								"type": "DatasetReference"
							},
							"name": "source1"
						},
						{
							"dataset": {
								"referenceName": "DepartmentsDataSet",
								"type": "DatasetReference"
							},
							"name": "source2"
						}
					],
					"sinks": [
						{
							"dataset": {
								"referenceName": "DataFlowSinkDataSet",
								"type": "DatasetReference"
							},
							"name": "ItEmployees"
						},
						{
							"dataset": {
								"referenceName": "DataFlowSinkDataSet",
								"type": "DatasetReference"
							},
							"name": "HrEmployees"
						},
						{
							"dataset": {
								"referenceName": "DataFlowSinkDataSet",
								"type": "DatasetReference"
							},
							"name": "PayrollEmployees"
						}
					],
					"transformations": [
						{
							"name": "split1"
						}
					],
					"scriptLines": [
						"source(output(",
						"          empid as string,",
						"          name as string,",
						"          country as string,",
						"          department as string",
						"     ),",
						"     allowSchemaDrift: true,",
						"     validateSchema: false,",
						"     ignoreNoFilesFound: false) ~> source1",
						"source(output(",
						"          depid as string,",
						"          depname as string",
						"     ),",
						"     allowSchemaDrift: true,",
						"     validateSchema: false,",
						"     ignoreNoFilesFound: false) ~> source2",
						"source1 split(equals(department,\"1\"),",
						"     equals(department,\"2\"),",
						"     disjoint: false) ~> split1@(ITEmployees, HREmployees, PAYROLLEmployees)",
						"split1@ITEmployees sink(allowSchemaDrift: true,",
						"     validateSchema: false,",
						"     partitionFileNames:['IT_Employees.csv'],",
						"     umask: 0022,",
						"     preCommands: [],",
						"     postCommands: [],",
						"     skipDuplicateMapInputs: true,",
						"     skipDuplicateMapOutputs: true,",
						"     partitionBy('hash', 1)) ~> ItEmployees",
						"split1@HREmployees sink(allowSchemaDrift: true,",
						"     validateSchema: false,",
						"     partitionFileNames:['HR_Employees.csv'],",
						"     umask: 0022,",
						"     preCommands: [],",
						"     postCommands: [],",
						"     skipDuplicateMapInputs: true,",
						"     skipDuplicateMapOutputs: true,",
						"     partitionBy('hash', 1)) ~> HrEmployees",
						"split1@PAYROLLEmployees sink(allowSchemaDrift: true,",
						"     validateSchema: false,",
						"     partitionFileNames:['Payroll_Employees.csv'],",
						"     umask: 0022,",
						"     preCommands: [],",
						"     postCommands: [],",
						"     skipDuplicateMapInputs: true,",
						"     skipDuplicateMapOutputs: true,",
						"     partitionBy('hash', 1)) ~> PayrollEmployees"
					]
				}
			},
			"dependsOn": []
		},
		{
			"name": "[concat(parameters('factoryName'), '/Derived_Column_DataFlow')]",
			"type": "Microsoft.DataFactory/factories/dataflows",
			"apiVersion": "2018-06-01",
			"properties": {
				"type": "MappingDataFlow",
				"typeProperties": {
					"sources": [
						{
							"dataset": {
								"referenceName": "EmployeeDataSet",
								"type": "DatasetReference"
							},
							"name": "source1"
						}
					],
					"sinks": [
						{
							"dataset": {
								"referenceName": "DataFlowSinkDataSet",
								"type": "DatasetReference"
							},
							"name": "sink1"
						}
					],
					"transformations": [
						{
							"name": "derivedColumn1"
						}
					],
					"scriptLines": [
						"source(output(",
						"          empid as string,",
						"          name as string,",
						"          country as string,",
						"          department as string",
						"     ),",
						"     allowSchemaDrift: true,",
						"     validateSchema: false,",
						"     ignoreNoFilesFound: false) ~> source1",
						"source1 derive(country = upper(country),",
						"          NewCountryColumn = iif(isNull(country),\"Unknown\",upper(country))) ~> derivedColumn1",
						"derivedColumn1 sink(allowSchemaDrift: true,",
						"     validateSchema: false,",
						"     partitionFileNames:['Derived_Column_Data.csv'],",
						"     umask: 0022,",
						"     preCommands: [],",
						"     postCommands: [],",
						"     skipDuplicateMapInputs: true,",
						"     skipDuplicateMapOutputs: true,",
						"     partitionBy('hash', 1)) ~> sink1"
					]
				}
			},
			"dependsOn": []
		},
		{
			"name": "[concat(parameters('factoryName'), '/Employee_DataFlow')]",
			"type": "Microsoft.DataFactory/factories/dataflows",
			"apiVersion": "2018-06-01",
			"properties": {
				"type": "MappingDataFlow",
				"typeProperties": {
					"sources": [
						{
							"dataset": {
								"referenceName": "EmployeeDataSet",
								"type": "DatasetReference"
							},
							"name": "EmployeeData"
						},
						{
							"dataset": {
								"referenceName": "DepartmentsDataSet",
								"type": "DatasetReference"
							},
							"name": "DepartmentsData"
						}
					],
					"sinks": [
						{
							"dataset": {
								"referenceName": "DataFlowSinkDataSet",
								"type": "DatasetReference"
							},
							"name": "sink"
						}
					],
					"transformations": [
						{
							"name": "join1"
						},
						{
							"name": "ModifyColumns1",
							"description": "Autogenerated by data preview actions"
						}
					],
					"scriptLines": [
						"source(output(",
						"          empid as string,",
						"          name as string,",
						"          country as string,",
						"          department as string",
						"     ),",
						"     allowSchemaDrift: true,",
						"     validateSchema: false,",
						"     ignoreNoFilesFound: false) ~> EmployeeData",
						"source(output(",
						"          depid as string,",
						"          depname as string",
						"     ),",
						"     allowSchemaDrift: true,",
						"     validateSchema: false,",
						"     ignoreNoFilesFound: false) ~> DepartmentsData",
						"DepartmentsData, ModifyColumns1 join(department == depid,",
						"     joinType:'inner',",
						"     matchType:'exact',",
						"     ignoreSpaces: false,",
						"     broadcast: 'auto')~> join1",
						"EmployeeData derive(country = upper(country)) ~> ModifyColumns1",
						"join1 sink(allowSchemaDrift: true,",
						"     validateSchema: false,",
						"     partitionFileNames:['EmpDepData.csv'],",
						"     umask: 0022,",
						"     preCommands: [],",
						"     postCommands: [],",
						"     skipDuplicateMapInputs: true,",
						"     skipDuplicateMapOutputs: true,",
						"     mapColumn(",
						"          empid,",
						"          name,",
						"          country,",
						"          depname",
						"     ),",
						"     partitionBy('hash', 1)) ~> sink"
					]
				}
			},
			"dependsOn": []
		},
		{
			"name": "[concat(parameters('factoryName'), '/Exists_DataFlow')]",
			"type": "Microsoft.DataFactory/factories/dataflows",
			"apiVersion": "2018-06-01",
			"properties": {
				"type": "MappingDataFlow",
				"typeProperties": {
					"sources": [
						{
							"dataset": {
								"referenceName": "Employees2_Dataset",
								"type": "DatasetReference"
							},
							"name": "source1"
						},
						{
							"dataset": {
								"referenceName": "DepartmentsDataSet",
								"type": "DatasetReference"
							},
							"name": "source2"
						}
					],
					"sinks": [
						{
							"dataset": {
								"referenceName": "DataFlowSinkDataSet",
								"type": "DatasetReference"
							},
							"name": "sink1"
						}
					],
					"transformations": [
						{
							"name": "exists1"
						}
					],
					"scriptLines": [
						"source(output(",
						"          empid as string,",
						"          name as string,",
						"          country as string,",
						"          department as string",
						"     ),",
						"     allowSchemaDrift: true,",
						"     validateSchema: false,",
						"     ignoreNoFilesFound: false) ~> source1",
						"source(output(",
						"          depid as string,",
						"          depname as string",
						"     ),",
						"     allowSchemaDrift: true,",
						"     validateSchema: false,",
						"     ignoreNoFilesFound: false) ~> source2",
						"source1, source2 exists(department == depid,",
						"     negate:false,",
						"     partitionBy('roundRobin', 2),",
						"     broadcast: 'auto')~> exists1",
						"exists1 sink(allowSchemaDrift: true,",
						"     validateSchema: false,",
						"     partitionFileNames:['Employee_Exists.csv'],",
						"     umask: 0022,",
						"     preCommands: [],",
						"     postCommands: [],",
						"     skipDuplicateMapInputs: true,",
						"     skipDuplicateMapOutputs: true,",
						"     partitionBy('hash', 1)) ~> sink1"
					]
				}
			},
			"dependsOn": []
		},
		{
			"name": "[concat(parameters('factoryName'), '/Filter_Department3_Employees_DataFlow')]",
			"type": "Microsoft.DataFactory/factories/dataflows",
			"apiVersion": "2018-06-01",
			"properties": {
				"type": "MappingDataFlow",
				"typeProperties": {
					"sources": [
						{
							"dataset": {
								"referenceName": "EmployeeDataSet",
								"type": "DatasetReference"
							},
							"name": "EmployeeData"
						}
					],
					"sinks": [
						{
							"dataset": {
								"referenceName": "DataFlowSinkDataSet",
								"type": "DatasetReference"
							},
							"name": "sink1"
						}
					],
					"transformations": [
						{
							"name": "filter1"
						}
					],
					"scriptLines": [
						"source(output(",
						"          empid as string,",
						"          name as string,",
						"          country as string,",
						"          department as string",
						"     ),",
						"     allowSchemaDrift: true,",
						"     validateSchema: false,",
						"     ignoreNoFilesFound: false) ~> EmployeeData",
						"EmployeeData filter(equals(department, \"3\")) ~> filter1",
						"filter1 sink(allowSchemaDrift: true,",
						"     validateSchema: false,",
						"     partitionFileNames:['Department3Employees'],",
						"     umask: 0022,",
						"     preCommands: [],",
						"     postCommands: [],",
						"     skipDuplicateMapInputs: true,",
						"     skipDuplicateMapOutputs: true,",
						"     partitionBy('hash', 1)) ~> sink1"
					]
				}
			},
			"dependsOn": []
		},
		{
			"name": "[concat(parameters('factoryName'), '/Flatten_DataFlow')]",
			"type": "Microsoft.DataFactory/factories/dataflows",
			"apiVersion": "2018-06-01",
			"properties": {
				"type": "MappingDataFlow",
				"typeProperties": {
					"sources": [
						{
							"dataset": {
								"referenceName": "Employee_Json_Dataset",
								"type": "DatasetReference"
							},
							"name": "source1"
						}
					],
					"sinks": [
						{
							"dataset": {
								"referenceName": "DataFlowSinkJsonDataSet",
								"type": "DatasetReference"
							},
							"name": "sink1"
						}
					],
					"transformations": [
						{
							"name": "flatten1"
						}
					],
					"scriptLines": [
						"source(output(",
						"          Address as (country as string, state as string, zipcode as string),",
						"          Contact as (Phone as string, email as string),",
						"          id as string,",
						"          name as string,",
						"          skills as string[]",
						"     ),",
						"     allowSchemaDrift: true,",
						"     validateSchema: false,",
						"     ignoreNoFilesFound: false,",
						"     documentForm: 'arrayOfDocuments') ~> source1",
						"source1 foldDown(unroll(skills),",
						"     mapColumn(",
						"          id,",
						"          name,",
						"          skills,",
						"          Address,",
						"          Contact",
						"     ),",
						"     partitionBy('hash', 1),",
						"     skipDuplicateMapInputs: false,",
						"     skipDuplicateMapOutputs: false) ~> flatten1",
						"flatten1 sink(allowSchemaDrift: true,",
						"     validateSchema: false,",
						"     partitionFileNames:['Flatten_DataFlow_output.json'],",
						"     umask: 0022,",
						"     preCommands: [],",
						"     postCommands: [],",
						"     skipDuplicateMapInputs: true,",
						"     skipDuplicateMapOutputs: true,",
						"     partitionBy('hash', 1)) ~> sink1"
					]
				}
			},
			"dependsOn": []
		},
		{
			"name": "[concat(parameters('factoryName'), '/Lookup_DataFlow')]",
			"type": "Microsoft.DataFactory/factories/dataflows",
			"apiVersion": "2018-06-01",
			"properties": {
				"type": "MappingDataFlow",
				"typeProperties": {
					"sources": [
						{
							"dataset": {
								"referenceName": "Employees2_Dataset",
								"type": "DatasetReference"
							},
							"name": "EmployeeDataset"
						},
						{
							"dataset": {
								"referenceName": "DepartmentsDataSet",
								"type": "DatasetReference"
							},
							"name": "DepartmentDataset"
						}
					],
					"sinks": [
						{
							"dataset": {
								"referenceName": "DataFlowSinkDataSet",
								"type": "DatasetReference"
							},
							"name": "sink1"
						}
					],
					"transformations": [
						{
							"name": "lookup1"
						}
					],
					"scriptLines": [
						"source(output(",
						"          empid as string,",
						"          name as string,",
						"          country as string,",
						"          department as string",
						"     ),",
						"     allowSchemaDrift: true,",
						"     validateSchema: false,",
						"     ignoreNoFilesFound: false) ~> EmployeeDataset",
						"source(output(",
						"          depid as string,",
						"          depname as string",
						"     ),",
						"     allowSchemaDrift: true,",
						"     validateSchema: false,",
						"     ignoreNoFilesFound: false) ~> DepartmentDataset",
						"EmployeeDataset, DepartmentDataset lookup(department == depid,",
						"     multiple: false,",
						"     pickup: 'any',",
						"     broadcast: 'auto')~> lookup1",
						"lookup1 sink(allowSchemaDrift: true,",
						"     validateSchema: false,",
						"     partitionFileNames:['Lookup_DataFlow_Result.csv'],",
						"     umask: 0022,",
						"     preCommands: [],",
						"     postCommands: [],",
						"     skipDuplicateMapInputs: true,",
						"     skipDuplicateMapOutputs: true,",
						"     partitionBy('hash', 1)) ~> sink1"
					]
				}
			},
			"dependsOn": []
		},
		{
			"name": "[concat(parameters('factoryName'), '/New_Branch_DataFlow')]",
			"type": "Microsoft.DataFactory/factories/dataflows",
			"apiVersion": "2018-06-01",
			"properties": {
				"type": "MappingDataFlow",
				"typeProperties": {
					"sources": [
						{
							"dataset": {
								"referenceName": "Employees2_Dataset",
								"type": "DatasetReference"
							},
							"name": "EmployeeData"
						},
						{
							"dataset": {
								"referenceName": "DepartmentsDataSet",
								"type": "DatasetReference"
							},
							"name": "DepartmentData"
						}
					],
					"sinks": [
						{
							"dataset": {
								"referenceName": "DataFlowSinkDataSet",
								"type": "DatasetReference"
							},
							"name": "OutputSink"
						},
						{
							"dataset": {
								"referenceName": "DataFlowSinkDataSet",
								"type": "DatasetReference"
							},
							"name": "sink1"
						}
					],
					"transformations": [
						{
							"name": "aggregate1"
						},
						{
							"name": "join1"
						}
					],
					"scriptLines": [
						"source(output(",
						"          empid as string,",
						"          name as string,",
						"          country as string,",
						"          department as string",
						"     ),",
						"     allowSchemaDrift: true,",
						"     validateSchema: false,",
						"     ignoreNoFilesFound: false) ~> EmployeeData",
						"source(output(",
						"          depid as string,",
						"          depname as string",
						"     ),",
						"     allowSchemaDrift: true,",
						"     validateSchema: false,",
						"     ignoreNoFilesFound: false) ~> DepartmentData",
						"EmployeeData aggregate(groupBy(department),",
						"     Total_Employees = count(empid)) ~> aggregate1",
						"EmployeeData, DepartmentData join(department == depid,",
						"     joinType:'inner',",
						"     matchType:'exact',",
						"     ignoreSpaces: false,",
						"     broadcast: 'auto')~> join1",
						"aggregate1 sink(allowSchemaDrift: true,",
						"     validateSchema: false,",
						"     partitionFileNames:['New_Branch_Aggregated_Data.csv'],",
						"     umask: 0022,",
						"     preCommands: [],",
						"     postCommands: [],",
						"     skipDuplicateMapInputs: true,",
						"     skipDuplicateMapOutputs: true,",
						"     partitionBy('hash', 1)) ~> OutputSink",
						"join1 sink(allowSchemaDrift: true,",
						"     validateSchema: false,",
						"     partitionFileNames:['New_Branch_Join_Data.csv'],",
						"     umask: 0022,",
						"     preCommands: [],",
						"     postCommands: [],",
						"     skipDuplicateMapInputs: true,",
						"     skipDuplicateMapOutputs: true,",
						"     partitionBy('hash', 1)) ~> sink1"
					]
				}
			},
			"dependsOn": []
		},
		{
			"name": "[concat(parameters('factoryName'), '/Pivot_DataFlow')]",
			"type": "Microsoft.DataFactory/factories/dataflows",
			"apiVersion": "2018-06-01",
			"properties": {
				"type": "MappingDataFlow",
				"typeProperties": {
					"sources": [
						{
							"dataset": {
								"referenceName": "Employees3Dataset",
								"type": "DatasetReference"
							},
							"name": "Employee3Data"
						}
					],
					"sinks": [
						{
							"dataset": {
								"referenceName": "DataFlowSinkDataSet",
								"type": "DatasetReference"
							},
							"name": "sink1"
						}
					],
					"transformations": [
						{
							"name": "pivot1"
						}
					],
					"scriptLines": [
						"source(output(",
						"          id as string,",
						"          name as string,",
						"          gender as string,",
						"          country as string,",
						"          department as string",
						"     ),",
						"     allowSchemaDrift: true,",
						"     validateSchema: false,",
						"     ignoreNoFilesFound: false) ~> Employee3Data",
						"Employee3Data pivot(groupBy(department),",
						"     pivotBy(gender),",
						"     {} = count(id),",
						"     columnNaming: 'Total_$N$V_Employees',",
						"     lateral: true) ~> pivot1",
						"pivot1 sink(allowSchemaDrift: true,",
						"     validateSchema: false,",
						"     partitionFileNames:['Pivot_DataFlow_Result.csv'],",
						"     umask: 0022,",
						"     preCommands: [],",
						"     postCommands: [],",
						"     skipDuplicateMapInputs: true,",
						"     skipDuplicateMapOutputs: true,",
						"     partitionBy('hash', 1)) ~> sink1"
					]
				}
			},
			"dependsOn": []
		},
		{
			"name": "[concat(parameters('factoryName'), '/Select_DataFlow')]",
			"type": "Microsoft.DataFactory/factories/dataflows",
			"apiVersion": "2018-06-01",
			"properties": {
				"type": "MappingDataFlow",
				"typeProperties": {
					"sources": [
						{
							"dataset": {
								"referenceName": "Employees2_Dataset",
								"type": "DatasetReference"
							},
							"name": "source1"
						}
					],
					"sinks": [
						{
							"dataset": {
								"referenceName": "DataFlowSinkDataSet",
								"type": "DatasetReference"
							},
							"name": "sink1"
						}
					],
					"transformations": [
						{
							"name": "select1"
						}
					],
					"scriptLines": [
						"source(output(",
						"          empid as string,",
						"          name as string,",
						"          country as string,",
						"          department as string",
						"     ),",
						"     allowSchemaDrift: true,",
						"     validateSchema: false,",
						"     ignoreNoFilesFound: false) ~> source1",
						"source1 select(mapColumn(",
						"          empname = name,",
						"          empid,",
						"          country",
						"     ),",
						"     skipDuplicateMapInputs: true,",
						"     skipDuplicateMapOutputs: true) ~> select1",
						"select1 sink(allowSchemaDrift: true,",
						"     validateSchema: false,",
						"     partitionFileNames:['Select_DatFlow_Employee_Result.csv'],",
						"     umask: 0022,",
						"     preCommands: [],",
						"     postCommands: [],",
						"     skipDuplicateMapInputs: true,",
						"     skipDuplicateMapOutputs: true,",
						"     partitionBy('hash', 1)) ~> sink1"
					]
				}
			},
			"dependsOn": []
		},
		{
			"name": "[concat(parameters('factoryName'), '/Sort_Dataflow')]",
			"type": "Microsoft.DataFactory/factories/dataflows",
			"apiVersion": "2018-06-01",
			"properties": {
				"type": "MappingDataFlow",
				"typeProperties": {
					"sources": [
						{
							"dataset": {
								"referenceName": "Employees2_Dataset",
								"type": "DatasetReference"
							},
							"name": "source1"
						}
					],
					"sinks": [
						{
							"dataset": {
								"referenceName": "DataFlowSinkDataSet",
								"type": "DatasetReference"
							},
							"name": "sink1"
						}
					],
					"transformations": [
						{
							"name": "sort1"
						}
					],
					"scriptLines": [
						"source(output(",
						"          empid as string,",
						"          name as string,",
						"          country as string,",
						"          department as string",
						"     ),",
						"     allowSchemaDrift: true,",
						"     validateSchema: false,",
						"     ignoreNoFilesFound: false) ~> source1",
						"source1 sort(asc(name, true),",
						"     caseInsensitive: true) ~> sort1",
						"sort1 sink(allowSchemaDrift: true,",
						"     validateSchema: false,",
						"     partitionFileNames:['Sort_Dataflow_Result.csv'],",
						"     umask: 0022,",
						"     preCommands: [],",
						"     postCommands: [],",
						"     skipDuplicateMapInputs: true,",
						"     skipDuplicateMapOutputs: true,",
						"     partitionBy('hash', 1)) ~> sink1"
					]
				}
			},
			"dependsOn": []
		},
		{
			"name": "[concat(parameters('factoryName'), '/Surrogate_DataFlow')]",
			"type": "Microsoft.DataFactory/factories/dataflows",
			"apiVersion": "2018-06-01",
			"properties": {
				"type": "MappingDataFlow",
				"typeProperties": {
					"sources": [
						{
							"dataset": {
								"referenceName": "EmployeeDataSet",
								"type": "DatasetReference"
							},
							"name": "source1"
						}
					],
					"sinks": [
						{
							"dataset": {
								"referenceName": "DataFlowSinkDataSet",
								"type": "DatasetReference"
							},
							"name": "sink1"
						}
					],
					"transformations": [
						{
							"name": "surrogateKey1"
						}
					],
					"scriptLines": [
						"source(output(",
						"          empid as string,",
						"          name as string,",
						"          country as string,",
						"          department as string",
						"     ),",
						"     allowSchemaDrift: true,",
						"     validateSchema: false,",
						"     ignoreNoFilesFound: false) ~> source1",
						"source1 keyGenerate(output(id as long),",
						"     startAt: 1L,",
						"     stepValue: 1L) ~> surrogateKey1",
						"surrogateKey1 sink(allowSchemaDrift: true,",
						"     validateSchema: false,",
						"     partitionFileNames:['Surrogate_DataFlow_Output.csv'],",
						"     umask: 0022,",
						"     preCommands: [],",
						"     postCommands: [],",
						"     skipDuplicateMapInputs: true,",
						"     skipDuplicateMapOutputs: true,",
						"     partitionBy('hash', 1)) ~> sink1"
					]
				}
			},
			"dependsOn": []
		},
		{
			"name": "[concat(parameters('factoryName'), '/UnPivot_DataFlow')]",
			"type": "Microsoft.DataFactory/factories/dataflows",
			"apiVersion": "2018-06-01",
			"properties": {
				"type": "MappingDataFlow",
				"typeProperties": {
					"sources": [
						{
							"dataset": {
								"referenceName": "DelimitedText2",
								"type": "DatasetReference"
							},
							"name": "source1"
						}
					],
					"sinks": [
						{
							"dataset": {
								"referenceName": "DataFlowSinkDataSet",
								"type": "DatasetReference"
							},
							"name": "sink1"
						}
					],
					"transformations": [
						{
							"name": "unpivot1"
						}
					],
					"scriptLines": [
						"source(output(",
						"          PO as string,",
						"          Vendor as string,",
						"          Apple as string,",
						"          Mango as string",
						"     ),",
						"     allowSchemaDrift: true,",
						"     validateSchema: false,",
						"     ignoreNoFilesFound: false) ~> source1",
						"source1 unpivot(output(",
						"          Fruits as string,",
						"          Amount as string",
						"     ),",
						"     ungroupBy(PO,",
						"          Vendor),",
						"     lateral: true,",
						"     ignoreNullPivots: false) ~> unpivot1",
						"unpivot1 sink(allowSchemaDrift: true,",
						"     validateSchema: false,",
						"     partitionFileNames:['UnPivot_DataFlow_Output.csv'],",
						"     umask: 0022,",
						"     preCommands: [],",
						"     postCommands: [],",
						"     skipDuplicateMapInputs: true,",
						"     skipDuplicateMapOutputs: true,",
						"     partitionBy('hash', 1)) ~> sink1"
					]
				}
			},
			"dependsOn": []
		},
		{
			"name": "[concat(parameters('factoryName'), '/Union_DataFlow')]",
			"type": "Microsoft.DataFactory/factories/dataflows",
			"apiVersion": "2018-06-01",
			"properties": {
				"type": "MappingDataFlow",
				"typeProperties": {
					"sources": [
						{
							"dataset": {
								"referenceName": "Hr_Employees_File_Dataset",
								"type": "DatasetReference"
							},
							"name": "HrData"
						},
						{
							"dataset": {
								"referenceName": "It_Employees_File_Dataset",
								"type": "DatasetReference"
							},
							"name": "source2"
						},
						{
							"dataset": {
								"referenceName": "Payroll_Employees_File_Dataset",
								"type": "DatasetReference"
							},
							"name": "source3"
						}
					],
					"sinks": [
						{
							"dataset": {
								"referenceName": "DataFlowSinkDataSet",
								"type": "DatasetReference"
							},
							"name": "sink1"
						}
					],
					"transformations": [
						{
							"name": "union1"
						}
					],
					"scriptLines": [
						"source(output(",
						"          empid as string,",
						"          name as string,",
						"          country as string,",
						"          department as string",
						"     ),",
						"     allowSchemaDrift: true,",
						"     validateSchema: false,",
						"     ignoreNoFilesFound: false) ~> HrData",
						"source(output(",
						"          empid as string,",
						"          name as string,",
						"          country as string,",
						"          department as string",
						"     ),",
						"     allowSchemaDrift: true,",
						"     validateSchema: false,",
						"     ignoreNoFilesFound: false) ~> source2",
						"source(output(",
						"          empid as string,",
						"          name as string,",
						"          country as string,",
						"          department as string",
						"     ),",
						"     allowSchemaDrift: true,",
						"     validateSchema: false,",
						"     ignoreNoFilesFound: false) ~> source3",
						"HrData, source2, source3 union(byName: true)~> union1",
						"union1 sink(allowSchemaDrift: true,",
						"     validateSchema: false,",
						"     partitionFileNames:['Union_Employees.csv'],",
						"     umask: 0022,",
						"     preCommands: [],",
						"     postCommands: [],",
						"     skipDuplicateMapInputs: true,",
						"     skipDuplicateMapOutputs: true,",
						"     partitionBy('hash', 1)) ~> sink1"
					]
				}
			},
			"dependsOn": []
		},
		{
			"name": "[concat(parameters('factoryName'), '/Window_Functions_DataFlow')]",
			"type": "Microsoft.DataFactory/factories/dataflows",
			"apiVersion": "2018-06-01",
			"properties": {
				"type": "MappingDataFlow",
				"typeProperties": {
					"sources": [
						{
							"dataset": {
								"referenceName": "Employees_Window_Func_Dataset",
								"type": "DatasetReference"
							},
							"name": "source1"
						}
					],
					"sinks": [
						{
							"dataset": {
								"referenceName": "DataFlowSinkDataSet",
								"type": "DatasetReference"
							},
							"name": "sink1"
						}
					],
					"transformations": [
						{
							"name": "window1"
						}
					],
					"scriptLines": [
						"source(output(",
						"          id as string,",
						"          name as string,",
						"          gender as string,",
						"          country as string,",
						"          salary as integer,",
						"          department as string",
						"     ),",
						"     allowSchemaDrift: true,",
						"     validateSchema: false,",
						"     ignoreNoFilesFound: false) ~> source1",
						"source1 window(over(department),",
						"     asc(salary, true),",
						"     Rank = rank(),",
						"          DenseRank = denseRank(),",
						"          Sum = sum(salary)) ~> window1",
						"window1 sink(allowSchemaDrift: true,",
						"     validateSchema: false,",
						"     partitionFileNames:['Window_Function_DataFlow_Output.csv'],",
						"     umask: 0022,",
						"     preCommands: [],",
						"     postCommands: [],",
						"     skipDuplicateMapInputs: true,",
						"     skipDuplicateMapOutputs: true,",
						"     partitionBy('hash', 1)) ~> sink1"
					]
				}
			},
			"dependsOn": []
		},
		{
			"name": "[concat(parameters('factoryName'), '/Aggregated_Employees_DataFlow_Pipeline')]",
			"type": "Microsoft.DataFactory/factories/pipelines",
			"apiVersion": "2018-06-01",
			"properties": {
				"activities": [
					{
						"name": "Data flow1",
						"type": "ExecuteDataFlow",
						"dependsOn": [],
						"policy": {
							"timeout": "0.12:00:00",
							"retry": 0,
							"retryIntervalInSeconds": 30,
							"secureOutput": false,
							"secureInput": false
						},
						"userProperties": [],
						"typeProperties": {
							"dataflow": {
								"referenceName": "Aggregation_Employees_Dataflow",
								"type": "DataFlowReference",
								"parameters": {},
								"datasetParameters": {
									"source1": {},
									"source2": {},
									"sink1": {}
								}
							},
							"staging": {},
							"compute": {
								"coreCount": 8,
								"computeType": "General"
							},
							"traceLevel": "Fine"
						}
					}
				],
				"policy": {
					"elapsedTimeMetric": {}
				},
				"annotations": []
			},
			"dependsOn": []
		},
		{
			"name": "[concat(parameters('factoryName'), '/Branch_DataFlow_Pipeline')]",
			"type": "Microsoft.DataFactory/factories/pipelines",
			"apiVersion": "2018-06-01",
			"properties": {
				"activities": [
					{
						"name": "Data flow1",
						"type": "ExecuteDataFlow",
						"dependsOn": [],
						"policy": {
							"timeout": "0.12:00:00",
							"retry": 0,
							"retryIntervalInSeconds": 30,
							"secureOutput": false,
							"secureInput": false
						},
						"userProperties": [],
						"typeProperties": {
							"dataflow": {
								"referenceName": "New_Branch_DataFlow",
								"type": "DataFlowReference",
								"parameters": {},
								"datasetParameters": {
									"EmployeeData": {},
									"DepartmentData": {},
									"OutputSink": {},
									"sink1": {}
								}
							},
							"staging": {},
							"compute": {
								"coreCount": 8,
								"computeType": "General"
							},
							"traceLevel": "Fine"
						}
					}
				],
				"policy": {
					"elapsedTimeMetric": {}
				},
				"annotations": []
			},
			"dependsOn": [
				"[concat(variables('factoryId'), '/dataflows/New_Branch_DataFlow')]"
			]
		},
		{
			"name": "[concat(parameters('factoryName'), '/Conditional_Split_DataFlow_Pipeline')]",
			"type": "Microsoft.DataFactory/factories/pipelines",
			"apiVersion": "2018-06-01",
			"properties": {
				"activities": [
					{
						"name": "Data flow1",
						"type": "ExecuteDataFlow",
						"dependsOn": [],
						"policy": {
							"timeout": "0.12:00:00",
							"retry": 0,
							"retryIntervalInSeconds": 30,
							"secureOutput": false,
							"secureInput": false
						},
						"userProperties": [],
						"typeProperties": {
							"dataflow": {
								"referenceName": "Conditional_Split_Dataflow",
								"type": "DataFlowReference",
								"parameters": {},
								"datasetParameters": {
									"source1": {},
									"source2": {},
									"ItEmployees": {},
									"HrEmployees": {},
									"PayrollEmployees": {}
								}
							},
							"staging": {},
							"compute": {
								"coreCount": 8,
								"computeType": "General"
							},
							"traceLevel": "Fine"
						}
					}
				],
				"policy": {
					"elapsedTimeMetric": {}
				},
				"annotations": []
			},
			"dependsOn": [
				"[concat(variables('factoryId'), '/dataflows/Conditional_Split_Dataflow')]"
			]
		},
		{
			"name": "[concat(parameters('factoryName'), '/Derived_Column_DataFlow_Pipeline')]",
			"type": "Microsoft.DataFactory/factories/pipelines",
			"apiVersion": "2018-06-01",
			"properties": {
				"activities": [
					{
						"name": "Data flow1",
						"type": "ExecuteDataFlow",
						"dependsOn": [],
						"policy": {
							"timeout": "0.12:00:00",
							"retry": 0,
							"retryIntervalInSeconds": 30,
							"secureOutput": false,
							"secureInput": false
						},
						"userProperties": [],
						"typeProperties": {
							"dataflow": {
								"referenceName": "Derived_Column_DataFlow",
								"type": "DataFlowReference",
								"parameters": {},
								"datasetParameters": {
									"source1": {},
									"sink1": {}
								}
							},
							"staging": {},
							"compute": {
								"coreCount": 8,
								"computeType": "General"
							},
							"traceLevel": "Fine"
						}
					}
				],
				"policy": {
					"elapsedTimeMetric": {}
				},
				"annotations": []
			},
			"dependsOn": [
				"[concat(variables('factoryId'), '/dataflows/Derived_Column_DataFlow')]"
			]
		},
		{
			"name": "[concat(parameters('factoryName'), '/Employee_Data_Flow_Execute_Pipeline')]",
			"type": "Microsoft.DataFactory/factories/pipelines",
			"apiVersion": "2018-06-01",
			"properties": {
				"activities": [
					{
						"name": "Employee_Data_Flow_Execute_Activity",
						"type": "ExecuteDataFlow",
						"dependsOn": [],
						"policy": {
							"timeout": "0.12:00:00",
							"retry": 0,
							"retryIntervalInSeconds": 30,
							"secureOutput": false,
							"secureInput": false
						},
						"userProperties": [],
						"typeProperties": {
							"dataflow": {
								"referenceName": "Employee_DataFlow",
								"type": "DataFlowReference",
								"parameters": {},
								"datasetParameters": {
									"EmployeeData": {},
									"DepartmentsData": {},
									"sink": {}
								}
							},
							"staging": {},
							"compute": {
								"coreCount": 8,
								"computeType": "General"
							},
							"traceLevel": "Fine"
						}
					}
				],
				"policy": {
					"elapsedTimeMetric": {}
				},
				"annotations": []
			},
			"dependsOn": [
				"[concat(variables('factoryId'), '/dataflows/Employee_DataFlow')]"
			]
		}
	]
}